Workbook
Name Finanzas: CatModulo!$B$2:$B$8
Name Fiscal: CatModulo!$C$2:$C$4
Name Impacto: CatModulo!$J$2:$J$4
Name Modulo: CatModulo!$A$2:$A$4
Name Probabilidad: CatModulo!$K$2:$K$4
Name Tipo: CatModulo!$L$1:$L$5
Name Utilerias: CatModulo!$D$2:$D$4

Sheet Dashboard
A1: 📊 DASHBOARD DE AVANCE DE PRUEBAS - PORTAL DE PROVEEDORES FBC
A3: RESUMEN EJECUTIVO
A5: Total Escenarios | B5: ✅ Pasó | C5: ❌ Falló | D5: 🔄 En Progreso | E5: ⏳ Pendiente | F5: 🚫 Bloqueado | G5: 🐛 Con Bug Jira | H5: % Avance (Pasó) | I5: % Abiertos/Fallidos | K5: ⚠️ ESCENARIOS FALLIDOS O BLOQUEADO
K6: =_xlfn.CONCAT("Total: ",(COUNTIF('Matriz de Pruebas'!F3:F989,"Falló")+COUNTIF('Matriz de Pruebas'!F3:F989,"Bloqueado"))," de ",COUNTA('Matriz de Pruebas'!F3:F989," escenarios")) -> Total: 2 de 709
A7: =COUNTA('Matriz de Pruebas'!F3:F989) -> 708 | B7: =COUNTIF('Matriz de Pruebas'!F3:F989,"Pasó") -> 266 | C7: =COUNTIF('Matriz de Pruebas'!F3:F989,"Falló") -> 2 | D7: =COUNTIF('Matriz de Pruebas'!F3:F989,"En Progreso") -> 1 | E7: =COUNTIF('Matriz de Pruebas'!F3:F989,"Pendiente") -> 439 | F7: =COUNTIF('Matriz de Pruebas'!F3:F989,"Bloqueado") -> 0 | G7: =COUNTIF('Matriz de Pruebas'!I3:I989,"*") -> 2 | H7: =IFERROR(COUNTIF('Matriz de Pruebas'!F3:F989,"Pasó")/COUNTA('Matriz de Pruebas'!F3:F989),0) -> 0.37570621 | I7: =IFERROR((COUNTIF('Matriz de Pruebas'!F3:F989,"Falló")+COUNTIF('Matriz de Pruebas'!F3:F989,"Bloqueado"))/COUNTA('Matriz de Pruebas'!F3:F989),0) -> 0.0028248588
K8: DESGLOSE POR PRIORIDAD
A9: BARRA DE AVANCE GENERAL | K9: Prioridad | L9: Total | M9: Fallaron | N9: % Fallo
A10: =IFERROR(REPT("█",ROUND(COUNTIF('Matriz de Pruebas'!F3:F19,"Pasó")/COUNTA('Matriz de Pruebas'!F3:F19)*50,0))&REPT("░",50-ROUND(COUNTIF('Matriz de Pruebas'!F3:F19,"Pasó")/COUNTA('Matriz de Pruebas'!F3:F19)*50,0)),"Sin datos") -> ░░░░░░░░░░░░░░░░░░░░░░░░░░░░░░░░░░░░░░░░░░░░░░░░░░ | K10: Critico | L10: =COUNTIF('Matriz de Pruebas'!E3:E989,"Critico") -> 31 | M10: {=SUMPRODUCT((EXACT('Matriz de Pruebas'!E3:E989,"Critico"))*(EXACT('Matriz de Pruebas'!F3:F989,"Falló")))} -> 2 | N10: {=IFERROR(SUMPRODUCT((EXACT('Matriz de Pruebas'!E3:E989,"Critico"))*(EXACT('Matriz de Pruebas'!F3:F989,"Falló")))/COUNTIF('Matriz de Pruebas'!E3:E989,"Critico"),0)} -> 0.064516129
K11: Alta | L11: =COUNTIF('Matriz de Pruebas'!E3:E989,"Alta") -> 275 | M11: {=SUMPRODUCT((EXACT('Matriz de Pruebas'!E3:E989,"Alta"))*(EXACT('Matriz de Pruebas'!F3:F989,"Falló")))} -> 0 | N11: {=IFERROR(SUMPRODUCT((EXACT('Matriz de Pruebas'!E3:E989,"Alta"))*(EXACT('Matriz de Pruebas'!F3:F989,"Falló")))/COUNTIF('Matriz de Pruebas'!E3:E989,"Alta"),0)} -> 0
A12: DESGLOSE POR ESTADO | K12: Media | L12: =COUNTIF('Matriz de Pruebas'!E3:E989,"Media") -> 390 | M12: {=SUMPRODUCT((EXACT('Matriz de Pruebas'!E3:E989,"Media"))*(EXACT('Matriz de Pruebas'!F3:F989,"Falló")))} -> 0 | N12: {=IFERROR(SUMPRODUCT((EXACT('Matriz de Pruebas'!E3:E989,"Media"))*(EXACT('Matriz de Pruebas'!F3:F989,"Falló")))/COUNTIF('Matriz de Pruebas'!E3:E989,"Media"),0)} -> 0
A13: Estado | B13: Cantidad | C13: % del Total | D13: Tendencia | K13: Baja | L13: =COUNTIF('Matriz de Pruebas'!E3:E989,"Baja") -> 4 | M13: {=SUMPRODUCT((EXACT('Matriz de Pruebas'!E3:E989,"Baja"))*(EXACT('Matriz de Pruebas'!F3:F989,"Falló")))} -> 0 | N13: {=IFERROR(SUMPRODUCT((EXACT('Matriz de Pruebas'!E3:E989,"Baja"))*(EXACT('Matriz de Pruebas'!F3:F989,"Falló")))/COUNTIF('Matriz de Pruebas'!E3:E989,"Baja"),0)} -> 0
A14: ✅ Pasó | B14: =COUNTIF('Matriz de Pruebas'!F3:F989,"Pasó") -> 266 | C14: =IFERROR(COUNTIF('Matriz de Pruebas'!F3:F19,"Pasó")/COUNTA('Matriz de Pruebas'!F3:F19),0) -> 0 | D14: =REPT("▓",ROUND(IFERROR(COUNTIF('Matriz de Pruebas'!F3:F19,"Pasó")/COUNTA('Matriz de Pruebas'!F3:F19),0)*20,0))
A15: ❌ Falló | B15: =COUNTIF('Matriz de Pruebas'!F3:F989,"Falló") -> 2 | C15: =IFERROR(COUNTIF('Matriz de Pruebas'!F3:F19,"Falló")/COUNTA('Matriz de Pruebas'!F3:F19),0) -> 0 | D15: =REPT("▓",ROUND(IFERROR(COUNTIF('Matriz de Pruebas'!F3:F19,"Falló")/COUNTA('Matriz de Pruebas'!F3:F19),0)*20,0))
A16: 🔄 En Progreso | B16: =COUNTIF('Matriz de Pruebas'!F3:F989,"En Progreso") -> 1 | C16: =IFERROR(COUNTIF('Matriz de Pruebas'!F3:F19,"En Progreso")/COUNTA('Matriz de Pruebas'!F3:F19),0) -> 0 | D16: =REPT("▓",ROUND(IFERROR(COUNTIF('Matriz de Pruebas'!F3:F19,"En Progreso")/COUNTA('Matriz de Pruebas'!F3:F19),0)*20,0))
A17: ⏳ Pendiente | B17: =COUNTIF('Matriz de Pruebas'!F3:F989,"Pendiente") -> 439 | C17: =IFERROR(COUNTIF('Matriz de Pruebas'!F3:F19,"Pendiente")/COUNTA('Matriz de Pruebas'!F3:F19),0) -> 1 | D17: =REPT("▓",ROUND(IFERROR(COUNTIF('Matriz de Pruebas'!F3:F19,"Pendiente")/COUNTA('Matriz de Pruebas'!F3:F19),0)*20,0)) -> ▓▓▓▓▓▓▓▓▓▓▓▓▓▓▓▓▓▓▓▓
A18: 🚫 Bloqueado | B18: =COUNTIF('Matriz de Pruebas'!F3:F989,"Bloqueado") -> 0 | C18: =IFERROR(COUNTIF('Matriz de Pruebas'!F3:F19,"Bloqueado")/COUNTA('Matriz de Pruebas'!F3:F19),0) -> 0 | D18: =REPT("▓",ROUND(IFERROR(COUNTIF('Matriz de Pruebas'!F3:F19,"Bloqueado")/COUNTA('Matriz de Pruebas'!F3:F19),0)*20,0))

Sheet Matriz de Pruebas
A1: 🧪 MATRIZ DE SEGUIMIENTO DE PRUEBAS
A2: ID | B2: Escenario de Prueba | C2: Módulo | D2: Submódulo | E2: Prioridad | F2: Estado | G2: Resultado Esperado | H2: Resultado Obtenido | I2: Vinculación Bug (ID Jira) | J2: Responsable QA | K2: Responsable Negocio (UAT) | L2: Responsable Dev | M2: Notas / Evidencia | N2: Fecha Ejecución | O2: Rol Usuario | P2: Pasos | Q2: Impacto | R2: Probabilidad | S2: Escenario Dependiente | T2: Tipo Escenario | U2: Tipo
A3: REC 001 | B3: Validar botón primario único azul al consultar recepciones Disponibles con filtro fecha válido | C3: Finanzas | D3: Recepciones | E3: Media | F3: Pendiente | G3: Solo un botón primario visible en pantalla el "Exportar CSV" | J3: Marco Vezquez | K3: Nelva Flores | L3: David Montes | M3: Evidencia visual UI | O3: Proveedor – Mercancía | P3: 1.Login 2.Seleccionar fechas válidas 3.Consultar 4.Validar botones | Q3: Bajo | R3: Alta | T3: Consulta | U3: FrontEnd
A4: REC 002 | B4: Por default no presentar información hasta que el usuario seleccione los criterios de busqueda | C4: Finanzas | D4: Recepciones | E4: Media | F4: Pendiente | G4: Sin consulta de información | J4: Marco Vezquez | K4: Nelva Flores | L4: David Montes | M4: Evidencia visual UI | O4: Cualquie Rol | P4: Seleccionar opción de recepción | Q4: Bajo | R4: Alta | T4: Consulta | U4: FrontEnd
A5: REC 003 | B5: Validar el botón de limpiar, el cual limpia filtros de busqueda, consulta e información que exista cargada en pantalla | C5: Finanzas | D5: Recepciones | E5: Media | F5: Pendiente | G5: Limpia la pantalla de toda la información cargada | J5: Marco Vezquez | K5: Nelva Flores | L5: David Montes | M5: Evidencia visual UI | O5: Proveedor – Mercancía | P5: 1.Login 2.Seleccionar fechas válidas 3.Consultar 4.Validar botones | Q5: Bajo | R5: Alta | T5: Consulta | U5: FrontEnd
A6: REC 004 | B6: El campo de id de proveedor llenarno por default cuando tenga el rol de proveedor | C6: Finanzas | D6: Recepciones | E6: Media | F6: Pendiente | G6: Id del proveedor precargado | J6: Marco Vezquez | K6: Nelva Flores | L6: David Montes | M6: Evidencia visual UI | O6: Proveedor – Mercancía | Q6: Bajo | R6: Alta | T6: Consulta | U6: FrontEnd
A7: REC 005 | B7: El campo de id de proveedor permitir seleccionar cuando tenga el rol diferente a proveedor | C7: Finanzas | D7: Recepciones | E7: Media | F7: Pendiente | G7: Campo de captura activo | J7: Marco Vezquez | K7: Nelva Flores | L7: David Montes | M7: Evidencia visual UI | O7: Rol diferente a proveedor | Q7: Bajo | R7: Alta | T7: Consulta | U7: FrontEnd
A8: REC 006 | B8: Modal obligatorio cancelar recepción Disponible sin factura | C8: Finanzas | D8: Recepciones | E8: Media | F8: Pendiente | G8: Modal confirmación obligatorio antes de cancelar | J8: Marco Vezquez | K8: Nelva Flores | L8: David Montes | M8: Captura modal | O8: Proveedor – Mercancía | P8: 1.Filtrar 2.Seleccionar recepción 3.Cancelar | Q8: Alto | R8: Media | T8: Actualización | U8: FrontEnd
A9: REC 007 | B9: Calendario de filtro de fechas fijo sin desplazamiento | C9: Finanzas | D9: Recepciones | E9: Media | F9: Pendiente | G9: Calendario no genera scroll UI | J9: Marco Vezquez | K9: Nelva Flores | L9: David Montes | O9: Proveedor – Transporte | P9: 1.Abrir calendario | Q9: Medio | R9: Media | T9: Consulta | U9: FrontEnd
A10: REC 008 | B10: Validar formato moneda y fecha | C10: Finanzas | D10: Recepciones | E10: Media | F10: Pendiente | G10: $000.00 y dd/mm/yyyy correctos | J10: Marco Vezquez | K10: Nelva Flores | L10: David Montes | O10: Proveedor – Servicios | P10: 1.Consultar registros | Q10: Bajo | R10: Media | T10: Consulta | U10: FrontEnd
A11: REC 009 | B11: Validar los colores de cada estatus de la recepción que retorna el API Catálogo de catálogos | C11: Finanzas | D11: Recepciones | E11: Media | F11: Pendiente | G11: Colores consistentes por estatus | J11: Marco Vezquez | K11: Nelva Flores | L11: David Montes | O11: Proveedor – Indirectos | P11: 1.Consultar grid | Q11: Medio | R11: Media | T11: Consulta | U11: FrontEnd
A12: REC 010 | B12: Validar paginación centrada con 10 registros exactos | C12: Finanzas | D12: Recepciones | E12: Media | F12: Pendiente | G12: Paginación centrada y fija en 10 | J12: Marco Vezquez | K12: Nelva Flores | L12: David Montes | O12: Analista Financiero – General | P12: 1.Consultar lista | Q12: Medio | R12: Baja | T12: Consulta | U12: FrontEnd
A13: REC 011 | B13: Persistencia filtros navegación de pantalla secundaria primaria | C13: Finanzas | D13: Recepciones | E13: Media | F13: Pendiente | G13: Filtros se mantienen | J13: Marco Vezquez | K13: Nelva Flores | L13: David Montes | O13: Analista Financiero – Especializado | P13: 1.Filtrar 2.Navegar 3.Regresar | Q13: Alto | R13: Media | T13: Consulta | U13: FrontEnd
A14: REC 012 | B14: Validar columnas completas Admin Funcional | C14: Finanzas | D14: Recepciones | E14: Media | F14: Pendiente | G14: Todas columnas visibles | J14: Marco Vezquez | K14: Nelva Flores | L14: David Montes | O14: Administrador Funcional | P14: 1.Consultar grid | Q14: Alto | R14: Media | T14: Consulta | U14: FrontEnd
A15: REC 013 | B15: Mensaje UX sin resultados | C15: Finanzas | D15: Recepciones | E15: Media | F15: Pendiente | G15: Mensaje claro sin error técnico | J15: Marco Vezquez | K15: Nelva Flores | L15: David Montes | O15: Comprador | P15: 1.Buscar UUID inválido | Q15: Medio | R15: Alta | T15: Error | U15: FrontEnd
A16: REC 014 | B16: Calendario sin movimiento rol Gerente Transporte | C16: Finanzas | D16: Recepciones | E16: Media | F16: Pendiente | G16: UI estable | J16: Marco Vezquez | K16: Nelva Flores | L16: David Montes | O16: Gerente de Transporte | P16: 1.Abrir fechas | Q16: Medio | R16: Media | T16: Consulta | U16: FrontEnd
A17: REC 015 | B17: Consulta válida filtros fecha+estatus Disponible con factura | C17: Finanzas | D17: Recepciones | E17: Media | F17: Pendiente | G17: Datos correctos retornados | J17: Marco Vezquez | K17: Nelva Flores | L17: David Montes | O17: Proveedor – Mercancía | P17: 1.Aplicar filtros | Q17: Alto | R17: Alta | T17: Consulta | U17: FrontEnd
A18: REC 016 | B18: Consulta UUID exacto Consumida manual sin factura | C18: Finanzas | D18: Recepciones | E18: Media | F18: Pendiente | G18: Registro único correcto | J18: Marco Vezquez | K18: Nelva Flores | L18: David Montes | O18: Proveedor – Transporte | P18: 1.Ingresar UUID | Q18: Alto | R18: Media | T18: Consulta | U18: FrontEnd
A19: REC 017 | B19: Consulta documento parcial con múltiples coincidencias | C19: Finanzas | D19: Recepciones | E19: Media | F19: Pendiente | G19: Registros filtrados correctamente | J19: Marco Vezquez | K19: Nelva Flores | L19: David Montes | O19: Proveedor – Servicios | P19: 1.Ingresar doc parcial | Q19: Medio | R19: Media | T19: Consulta | U19: FrontEnd
A20: REC 018 | B20: Consulta acceso restringido tipo proveedor distinto | C20: Finanzas | D20: Recepciones | E20: Media | F20: Pendiente | G20: Acceso denegado | J20: Marco Vezquez | K20: Nelva Flores | L20: David Montes | O20: Proveedor – Indirectos | P20: 1.Intentar visualizar otro tipo | Q20: Alto | R20: Media | T20: Restricción | U20: FrontEnd
... A26: REC 024 | B26: Exportación XLSX alto volumen integridad datos | C26: Finanzas | D26: Recepciones | E26: Media | F26: Pendiente | G26: Archivo completo sin pérdida | J26: Marco Vezquez | K26: Nelva Flores | L26: David Montes | O26: Administrador del Sistema | P26: 1.Exportar XLSX | Q26: Alto | R26: Media | T26: Consulta | U26: FrontEnd
A27: REC 025 | B27: Llevar a una pantalla secundaria para relacionar factura CFDI válido Disponible | C27: Finanzas | D27: Recepciones | E27: Media | F27: Pendiente | G27: Relación exitosa | J27: Marco Vezquez | K27: Nelva Flores | L27: David Montes | O27: Proveedor – Mercancía | P27: 1.Seleccionar recepción 2.Relacionar | Q27: Alto | R27: Alta | S27: REC011 | T27: Actualización | U27: FrontEnd
A28: REC 026 | B28: Llevar a una pantalla secundaria para relación manual UUID válido coincidente | C28: Finanzas | D28: Recepciones | E28: Media | F28: Pendiente | G28: Relación completada | J28: Marco Vezquez | K28: Nelva Flores | L28: David Montes | O28: Proveedor – Transporte | P28: 1.Ingresar UUID válido | Q28: Alto | R28: Media | S28: REC012 | T28: Actualización | U28: FrontEnd
A29: REC 027 | B29: Llevar a una pantalla secundaria para ver artículos en Consumida con detalle completo | C29: Finanzas | D29: Recepciones | E29: Media | F29: Pendiente | G29: Información correcta | J29: Marco Vezquez | K29: Nelva Flores | L29: David Montes | O29: Proveedor – Servicios | P29: 1.Ver artículos | Q29: Medio | R29: Media | T29: Consulta | U29: FrontEnd
A30: REC 028 | B30: Llevar a una pantalla secundaria para cancelar recepción Disponible sin factura | C30: Finanzas | D30: Recepciones | E30: Media | F30: Pendiente | G30: Estatus cambia a 7 | J30: Marco Vezquez | K30: Nelva Flores | L30: David Montes | O30: Proveedor – Indirectos | P30: 1.Cancelar | Q30: Alto | R30: Media | S30: REC011 | T30: Actualización | U30: FrontEnd
A31: REC 029 | B31: Transición válida Disponible→Consumida | C31: Finanzas | D31: Recepciones | E31: Media | F31: Pendiente | G31: Cambio correcto estatus | J31: Marco Vezquez | K31: Nelva Flores | L31: David Montes | O31: Analista Financiero – General | P31: 1.Ejecutar acción | Q31: Alto | R31: Alta | S31: REC011 | T31: Actualización | U31: FrontEnd
A32: REC 030 | B32: Transición Consumida→Contable | C32: Finanzas | D32: Recepciones | E32: Media | F32: Pendiente | G32: Estatus 3 aplicado | J32: Marco Vezquez | K32: Nelva Flores | L32: David Montes | O32: Analista Financiero – Especializado | P32: 1.Procesar contable | Q32: Alto | R32: Media | S32: REC025 | T32: Actualización | U32: FrontEnd
A33: REC 031 | B33: Flujo Contable→Pago | C33: Finanzas | D33: Recepciones | E33: Media | F33: Pendiente | G33: Estatus 5 | J33: Marco Vezquez | K33: Nelva Flores | L33: David Montes | O33: Gerente Financiero | P33: 1.Procesar pago | Q33: Alto | R33: Alta | S33: REC026 | T33: Actualización | U33: FrontEnd
A34: REC 032 | B34: Flujo Pago→Pagada cierre | C34: Finanzas | D34: Recepciones | E34: Media | F34: Pendiente | G34: Estatus 6 | J34: Marco Vezquez | K34: Nelva Flores | L34: David Montes | O34: Administrador del Sistema | P34: 1.Validar pago | Q34: Alto | R34: Alta | S34: REC027 | T34: Actualización | U34: FrontEnd
A35: REC 033 | B35: Rechazo contable desde Consumida | C35: Finanzas | D35: Recepciones | E35: Media | F35: Pendiente | G35: Estatus 4 | J35: Marco Vezquez | K35: Nelva Flores | L35: David Montes | O35: Analista Financiero – Especializado | P35: 1.Rechazar | Q35: Alto | R35: Media | T35: Actualización | U35: FrontEnd
A36: REC 034 | B36: Cancelar recepción Pagada no permitido | C36: Finanzas | D36: Recepciones | E36: Media | F36: Pendiente | G36: Acción bloqueada | J36: Marco Vezquez | K36: Nelva Flores | L36: David Montes | O36: Analista Financiero – General | P36: 1.Intentar cancelar | Q36: Alto | R36: Alta | T36: Restricción | U36: FrontEnd
A37: REC 035 | B37: Relacionar factura en Cancelada no permitido | C37: Finanzas | D37: Recepciones | E37: Media | F37: Pendiente | G37: Bloqueo acción | J37: Marco Vezquez | K37: Nelva Flores | L37: David Montes | O37: Proveedor – Transporte | P37: 1.Intentar relacionar | Q37: Alto | R37: Media | T37: Restricción | U37: FrontEnd
A38: REC 036 | B38: Validar invisibilidad de estatus de recepción Borrado lógico | C38: Finanzas | D38: Recepciones | E38: Media | F38: Pendiente | G38: Registro no visible | J38: Marco Vezquez | K38: Nelva Flores | L38: David Montes | O38: Administrador Funcional | P38: 1.Buscar registro | Q38: Alto | R38: Media | T38: Restricción | U38: FrontEnd
A39: REC 037 | B39: Transición inválida Disponible→Pagada | C39: Finanzas | D39: Recepciones | E39: Media | F39: Pendiente | G39: API rechaza operación | J39: Marco Vezquez | K39: Nelva Flores | L39: David Montes | O39: Gerente Financiero | P39: 1.Intentar salto | Q39: Alto | R39: Media | T39: Restricción | U39: FrontEnd
A40: REC 038 | B40: Acceso datos proveedor distinto bloqueado | C40: Finanzas | D40: Recepciones | E40: Media | F40: Pendiente | G40: Acceso denegado | J40: Marco Vezquez | K40: Nelva Flores | L40: David Montes | O40: Proveedor – Mercancía | P40: 1.Intentar acceso | Q40: Alto | R40: Alta | T40: Seguridad | U40: FrontEnd
A41: REC 039 | B41: Columnas sensibles de columnas ocultas para rol de proveedor (Columna Id Proveedor, Nombre Proveedor) | C41: Finanzas | D41: Recepciones | E41: Media | F41: Pendiente | G41: Columnas restringidas | J41: Marco Vezquez | K41: Nelva Flores | L41: David Montes | O41: Gerente Comercial | P41: 1.Validar columnas | Q41: Medio | R41: Media | T41: Restricción | U41: FrontEnd
A42: REC 040 | B42: Acceso URL sin autenticación | C42: Finanzas | D42: Recepciones | E42: Media | F42: Pendiente | G42: Redirección login | J42: Marco Vezquez | K42: Nelva Flores | L42: David Montes | O42: Usuario anónimo | P42: 1.Abrir URL | Q42: Alto | R42: Alta | T42: Seguridad | U42: FrontEnd
A43: REC 041 | B43: Manipulación payload UUID backend | C43: Finanzas | D43: Recepciones | E43: Media | F43: Pendiente | G43: Rechazo seguridad | J43: Marco Vezquez | K43: Nelva Flores | L43: David Montes | O43: Administrador del Sistema | P43: 1.Alterar request | Q43: Alto | R43: Alta | T43: Seguridad | U43: FrontEnd
A44: REC 042 | B44: UUID inválido longitud incorrecta | C44: Finanzas | D44: Recepciones | E44: Media | F44: Pendiente | G44: Validación error | J44: Marco Vezquez | K44: Nelva Flores | L44: David Montes | O44: Proveedor – Servicios | P44: 1.Ingresar inválido | Q44: Medio | R44: Alta | T44: Error | U44: FrontEnd
A45: REC 043 | B45: Fecha mayor 6 meses bloqueada | C45: Finanzas | D45: Recepciones | E45: Media | F45: Pendiente | G45: Error validación | J45: Marco Vezquez | K45: Nelva Flores | L45: David Montes | O45: Gerente Comercial | P45: 1.Filtrar fechas inválidas | Q45: Alto | R45: Alta | T45: Error | U45: FrontEnd
A46: REC 044 | B46: Consulta sin filtros bloqueada | C46: Finanzas | D46: Recepciones | E46: Media | F46: Pendiente | G46: No ejecuta consulta | J46: Marco Vezquez | K46: Nelva Flores | L46: David Montes | O46: Administrador Funcional | P46: 1.Buscar sin filtros | Q46: Alto | R46: Alta | T46: Restricción | U46: FrontEnd
... A53: REC 051 | B53: Performance carga >1000 registros | C53: Finanzas | D53: Recepciones | E53: Media | F53: Pendiente | G53: Tiempo <3 segundos | J53: Marco Vezquez | K53: Nelva Flores | L53: David Montes | O53: Analista Financiero – General | P53: 1.Ejecutar consulta | Q53: Alto | R53: Media | T53: Consulta | U53: FrontEnd
A54: CAP 001 | B54: Validar botón primario único azul en consulta de cartas porte con fechas válidas | C54: Finanzas | D54: Carta Porte | E54: Media | F54: Pendiente | G54: Solo un botón azul visible | J54: Paola Leon | K54: Diana Hernandez | L54: Fernando | M54: UI consistente | O54: Proveedor – Transporte | P54: 1.Login 2.Filtrar fechas 3.Consultar 4.Validar botón | Q54: Alto | R54: Media | T54: Consulta | U54: FrontEnd
A55: CAP 002 | B55: Por default no presentar información hasta que el usuario seleccione los criterios de busqueda | C55: Finanzas | D55: Carta Porte | E55: Media | F55: Pendiente | G55: Sin consulta de información | J55: Paola Leon | K55: Diana Hernandez | L55: Fernando | M55: Evidencia visual UI | O55: Cualquie Rol | P55: Seleccionar opción de Carta Porte | Q55: Bajo | R55: Alta | T55: Consulta | U55: FrontEnd
A56: CAP 003 | B56: Validar el botón de limpiar, el cual limpia filtros de busqueda, consulta e información que exista cargada en pantalla | C56: Finanzas | D56: Carta Porte | E56: Media | F56: Pendiente | G56: Limpia la pantalla de toda la información cargada | J56: Paola Leon | K56: Diana Hernandez | L56: Fernando | M56: UI consistente | O56: Proveedor – Transporte | P56: 1.Login 2.Filtrar fechas 3.Consultar 4.Validar limpiar | Q56: Medio | R56: Media | T56: Consulta | U56: FrontEnd
A57: CAP 004 | B57: Modal obligatorio al cancelar guía Pendiente de OC | C57: Finanzas | D57: Carta Porte | E57: Media | F57: Pendiente | G57: Modal de confirmación obligatorio | J57: Paola Leon | K57: Diana Hernandez | L57: Fernando | M57: Evidencia modal | O57: Proveedor – Transporte | P57: 1.Buscar guía 2.Cancelar | Q57: Alto | R57: Media | T57: Actualización | U57: FrontEnd
A58: CAP 005 | B58: Calendario fijo sin desplazamiento en filtro fechas | C58: Finanzas | D58: Carta Porte | E58: Media | F58: Pendiente | G58: Calendario estable sin scroll | J58: Paola Leon | K58: Diana Hernandez | L58: Fernando | O58: Analista Financiero – General | P58: 1.Abrir calendario | Q58: Medio | R58: Media | T58: Consulta | U58: FrontEnd
A59: CAP 006 | B59: Validar colores de estatus según API del catálogo de catálogos | C59: Finanzas | D59: Carta Porte | E59: Media | F59: Pendiente | G59: Colores correctos | J59: Paola Leon | K59: Diana Hernandez | L59: Fernando | O59: Analista Financiero – Especializado | P59: 1.Visualizar grid | Q59: Medio | R59: Media | T59: Consulta | U59: FrontEnd
A60: CAP 007 | B60: Validar formato fechas dd/mm/yyyy en grid | C60: Finanzas | D60: Carta Porte | E60: Media | F60: Pendiente | G60: Formato correcto | J60: Paola Leon | K60: Diana Hernandez | L60: Fernando | O60: Gerente Financiero | P60: 1.Ver fechas | Q60: Bajo | R60: Media | T60: Consulta | U60: FrontEnd
A61: CAP 008 | B61: Validar orden correcto columnas en grid: oGuia de embarque o Placa o Placa remolque o Origen o Tipo de entrega o Número de orden compra o Número de proveedor o Nombre de proveedor o Fecha de entrega o Fecha de envió o Fecha de registro o Estatus o Acciones | C61: Finanzas | D61: Carta Porte | E61: Media | F61: Pendiente | G61: Orden definido respetado | J61: Paola Leon | K61: Diana Hernandez | L61: Fernando | O61: Gerente de Transporte | P61: 1.Ver columnas | Q61: Medio | R61: Media | T61: Consulta | U61: FrontEnd
A62: CAP 009 | B62: Validar paginación centrada con 10 registros exactos | C62: Finanzas | D62: Carta Porte | E62: Media | F62: Pendiente | G62: Paginación centrada | J62: Paola Leon | K62: Diana Hernandez | L62: Fernando | O62: Comprador | P62: 1.Consultar | Q62: Medio | R62: Baja | T62: Consulta | U62: FrontEnd
A63: CAP 010 | B63: Persistencia de filtros tras navegación | C63: Finanzas | D63: Carta Porte | E63: Media | F63: Pendiente | G63: Filtros se mantienen | J63: Paola Leon | K63: Diana Hernandez | L63: Fernando | O63: Gerente Comercial | P63: 1.Filtrar 2.Navegar 3.Regresar | Q63: Alto | R63: Media | T63: Consulta | U63: FrontEnd
A64: CAP 011 | B64: Validar columnas completas rol administrador | C64: Finanzas | D64: Carta Porte | E64: Media | F64: Pendiente | G64: Columnas completas visibles | J64: Paola Leon | K64: Diana Hernandez | L64: Fernando | O64: Administrador Funcional | P64: 1.Consultar | Q64: Alto | R64: Media | T64: Consulta | U64: FrontEnd
A65: CAP 012 | B65: Mensaje UX sin resultados por filtro guía inválida | C65: Finanzas | D65: Carta Porte | E65: Media | F65: Pendiente | G65: Mensaje claro | J65: Paola Leon | K65: Diana Hernandez | L65: Fernando | O65: Administrador del Sistema | P65: 1.Buscar guía inválida | Q65: Medio | R65: Alta | T65: Error | U65: FrontEnd
A66: CAP 013 | B66: Consulta válida por fecha+proveedor Pendiente OC | C66: Finanzas | D66: Carta Porte | E66: Media | F66: Pendiente | G66: Resultados correctos | J66: Paola Leon | K66: Diana Hernandez | L66: Fernando | O66: Proveedor – Transporte | P66: 1.Filtrar | Q66: Alto | R66: Alta | T66: Consulta | U66: FrontEnd
A67: CAP 014 | B67: Consulta por guía exacta existente | C67: Finanzas | D67: Carta Porte | E67: Media | F67: Pendiente | G67: Registro único | J67: Paola Leon | K67: Diana Hernandez | L67: Fernando | O67: Analista Financiero – General | P67: 1.Buscar guía | Q67: Alto | R67: Media | T67: Consulta | U67: FrontEnd
A68: CAP 015 | B68: Consulta proveedor cargado automático rol proveedor | C68: Finanzas | D68: Carta Porte | E68: Media | F68: Pendiente | G68: Campo precargado | J68: Paola Leon | K68: Diana Hernandez | L68: Fernando | O68: Proveedor – Transporte | P68: 1.Login 2.Validar campo | Q68: Alto | R68: Alta | T68: Consulta | U68: FrontEnd
A69: CAP 016 | B69: Consulta proveedor editable rol analista | C69: Finanzas | D69: Carta Porte | E69: Media | F69: Pendiente | G69: Permite captura | J69: Paola Leon | K69: Diana Hernandez | L69: Fernando | O69: Analista Financiero – Especializado | P69: 1.Ingresar proveedor | Q69: Medio | R69: Media | T69: Consulta | U69: FrontEnd
... A78: CAP 025 | B78: Descargar guía CSV válida válida con el número de la guia y la fecha hora de descarga XXXX--yyyy-mm-dd-hh24-mi-ss.csv | C78: Finanzas | D78: Carta Porte | E78: Media | F78: Pendiente | G78: CSV correcto | J78: Paola Leon | K78: Diana Hernandez | L78: Fernando | O78: Analista Financiero – Especializado | P78: 1.Descargar CSV | Q78: Medio | R78: Media | T78: Consulta | U78: FrontEnd
A79: CAP 026 | B79: Cancelar guía Pendiente OC | C79: Finanzas | D79: Carta Porte | E79: Media | F79: Pendiente | G79: Estatus 9 aplicado | J79: Paola Leon | K79: Diana Hernandez | L79: Fernando | O79: Gerente Financiero | P79: 1.Cancelar guía | Q79: Alto | R79: Media | S79: CAP011 | T79: Actualización | U79: FrontEnd
A80: CAP 027 | B80: Actualizar guía válida con datos correctos | C80: Finanzas | D80: Carta Porte | E80: Media | F80: Pendiente | G80: Actualización exitosa | J80: Paola Leon | K80: Diana Hernandez | L80: Fernando | O80: Gerente de Transporte | P80: 1.Actualizar | Q80: Alto | R80: Media | T80: Actualización | U80: FrontEnd
A81: CAP 028 | B81: Transición Pendiente OC→Pendiente Facturar | C81: Finanzas | D81: Carta Porte | E81: Media | F81: Pendiente | G81: Transición exitosa | J81: Paola Leon | K81: Diana Hernandez | L81: Fernando | O81: Comprador | P81: 1.Ejecutar transición | Q81: Alto | R81: Alta | S81: CAP011 | T81: Actualización | U81: FrontEnd
A82: CAP 029 | B82: Transición Facturar→Pago manual | C82: Finanzas | D82: Carta Porte | E82: Media | F82: Pendiente | G82: Estatus 3 aplicado | J82: Paola Leon | K82: Diana Hernandez | L82: Fernando | O82: Gerente Comercial | P82: 1.Procesar factura | Q82: Alto | R82: Alta | S82: CAP026 | T82: Actualización | U82: FrontEnd
A83: CAP 030 | B83: Transición Pago→Contabilización automática | C83: Finanzas | D83: Carta Porte | E83: Media | F83: Pendiente | G83: Estatus 4 | J83: Paola Leon | K83: Diana Hernandez | L83: Fernando | O83: Administrador Funcional | P83: 1.Validar proceso | Q83: Alto | R83: Media | S83: CAP027 | T83: Actualización | U83: FrontEnd
A84: CAP 031 | B84: Contabilizada→Pagada flujo completo | C84: Finanzas | D84: Carta Porte | E84: Media | F84: Pendiente | G84: Estatus 7 | J84: Paola Leon | K84: Diana Hernandez | L84: Fernando | O84: Administrador del Sistema | P84: 1.Validar pago | Q84: Alto | R84: Alta | S84: CAP028 | T84: Actualización | U84: FrontEnd
A85: CAP 032 | B85: Rechazo contable y recuperación | C85: Finanzas | D85: Carta Porte | E85: Media | F85: Pendiente | G85: Estatus pasa a 6 y luego 5 | J85: Paola Leon | K85: Diana Hernandez | L85: Fernando | O85: Analista Financiero – Especializado | P85: 1.Rechazar 2.Reintentar | Q85: Alto | R85: Media | T85: Actualización | U85: FrontEnd
A86: CAP 033 | B86: Restricción cancelar guía pagada | C86: Finanzas | D86: Carta Porte | E86: Media | F86: Pendiente | G86: Acción bloqueada | J86: Paola Leon | K86: Diana Hernandez | L86: Fernando | O86: Proveedor – Transporte | P86: 1.Intentar cancelar | Q86: Alto | R86: Alta | T86: Restricción | U86: FrontEnd
A87: CAP 034 | B87: Restricción actualizar guía cancelada | C87: Finanzas | D87: Carta Porte | E87: Media | F87: Pendiente | G87: Acción no permitida | J87: Paola Leon | K87: Diana Hernandez | L87: Fernando | O87: Analista Financiero – General | P87: 1.Intentar actualizar | Q87: Alto | R87: Media | T87: Restricción | U87: FrontEnd
A88: CAP 035 | B88: Restricción acceso proveedor a otros datos | C88: Finanzas | D88: Carta Porte | E88: Media | F88: Pendiente | G88: Acceso denegado | J88: Paola Leon | K88: Diana Hernandez | L88: Fernando | O88: Proveedor – Transporte | P88: 1.Intentar ver otros | Q88: Alto | R88: Alta | T88: Seguridad | U88: FrontEnd
A89: CAP 036 | B89: Restricción transición inválida OC→Pagada | C89: Finanzas | D89: Carta Porte | E89: Media | F89: Pendiente | G89: API rechaza | J89: Paola Leon | K89: Diana Hernandez | L89: Fernando | O89: Analista Financiero – Especializado | P89: 1.Intentar salto | Q89: Alto | R89: Media | T89: Restricción | U89: FrontEnd
A90: CAP 037 | B90: Restricción visibilidad borrado lógico | C90: Finanzas | D90: Carta Porte | E90: Media | F90: Pendiente | G90: No visible | J90: Paola Leon | K90: Diana Hernandez | L90: Fernando | O90: Gerente Financiero | P90: 1.Buscar registro | Q90: Alto | R90: Media | T90: Restricción | U90: FrontEnd
A91: CAP 038 | B91: Restricción columnas sensibles ocultas | C91: Finanzas | D91: Carta Porte | E91: Media | F91: Pendiente | G91: Columnas restringidas | J91: Paola Leon | K91: Diana Hernandez | L91: Fernando | O91: Gerente Comercial | P91: 1.Validar columnas | Q91: Medio | R91: Media | T91: Restricción | U91: FrontEnd
A92: CAP 039 | B92: Seguridad acceso URL sin sesión | C92: Finanzas | D92: Carta Porte | E92: Media | F92: Pendiente | G92: Redirección login | J92: Paola Leon | K92: Diana Hernandez | L92: Fernando | O92: Usuario anónimo | P92: 1.Acceder URL | Q92: Alto | R92: Alta | T92: Seguridad | U92: FrontEnd
A93: CAP 040 | B93: Seguridad manipulación payload guía | C93: Finanzas | D93: Carta Porte | E93: Media | F93: Pendiente | G93: Rechazo backend | J93: Paola Leon | K93: Diana Hernandez | L93: Fernando | O93: Administrador del Sistema | P93: 1.Alterar request | Q93: Alto | R93: Alta | T93: Seguridad | U93: FrontEnd
A94: CAP 041 | B94: Error guía formato inválido | C94: Finanzas | D94: Carta Porte | E94: Media | F94: Pendiente | G94: Mensaje error validación | J94: Paola Leon | K94: Diana Hernandez | L94: Fernando | O94: Proveedor – Transporte | P94: 1.Ingresar inválido | Q94: Medio | R94: Alta | T94: Error | U94: FrontEnd
A95: CAP 042 | B95: Error fecha >6 meses | C95: Finanzas | D95: Carta Porte | E95: Media | F95: Pendiente | G95: Bloqueo consulta | J95: Paola Leon | K95: Diana Hernandez | L95: Fernando | O95: Analista Financiero – General | P95: 1.Filtrar inválido | Q95: Alto | R95: Alta | T95: Error | U95: FrontEnd
A96: CAP 043 | B96: Error consulta sin filtros | C96: Finanzas | D96: Carta Porte | E96: Media | F96: Pendiente | G96: No permite ejecución | J96: Paola Leon | K96: Diana Hernandez | L96: Fernando | O96: Analista Financiero – Especializado | P96: 1.Buscar sin filtros | Q96: Alto | R96: Alta | T96: Restricción | U96: FrontEnd
... A103: CAP 050 | B103: Performance carga masiva >1000 registros | C103: Finanzas | D103: Carta Porte | E103: Media | F103: Pendiente | G103: Respuesta <3s | J103: Paola Leon | K103: Diana Hernandez | L103: Fernando | O103: Analista Financiero – General | P103: 1.Consultar alto volumen | Q103: Alto | R103: Media | T103: Consulta | U103: FrontEnd
A104: DES 001 | B104: Validar botón primario único azul en consulta Pendiente NC con filtro fecha y tipo rebate | C104: Finanzas | D104: Descuentos comerciales | E104: Media | F104: Pendiente | G104: Solo un botón primario visible | J104: Ivan Cortes | K104: Liliana Preciado | L104: Fernando | M104: UI consistente | O104: Proveedor – Mercancía | P104: 1.Login 2.Filtrar 3.Validar UI | Q104: Medio | R104: Media | T104: Consulta | U104: FrontEnd
A105: DES 002 | B105: Por default no presentar información hasta que el usuario seleccione los criterios de busqueda | C105: Finanzas | D105: Descuentos comerciales | E105: Media | F105: Pendiente | G105: Sin consulta de información | J105: Ivan Cortes | K105: Liliana Preciado | L105: Fernando | M105: Evidencia visual UI | O105: Cualquie Rol | P105: Seleccionar opción de Descuento Comercial | Q105: Bajo | R105: Alta | T105: Consulta | U105: FrontEnd
A106: DES 003 | B106: Validar botón limpiar elimina filtros Documento y Estatus | C106: Finanzas | D106: Descuentos comerciales | E106: Media | F106: Pendiente | G106: Filtros reiniciados | J106: Ivan Cortes | K106: Liliana Preciado | L106: Fernando | O106: Proveedor – Transporte | P106: 1.Filtrar 2.Limpiar | Q106: Medio | R106: Media | T106: Consulta | U106: FrontEnd
A107: DES 004 | B107: Modal obligatorio cancelar descuento Pendiente NC sin NC relacionada | C107: Finanzas | D107: Descuentos comerciales | E107: Media | F107: Pendiente | G107: Modal confirmación mostrado | J107: Ivan Cortes | K107: Liliana Preciado | L107: Fernando | M107: Evidencia modal | O107: Proveedor – Servicios | P107: 1.Buscar 2.Cancelar | Q107: Alto | R107: Media | T107: Actualización | U107: FrontEnd
A108: DES 005 | B108: Calendario fijo sin desplazamiento en rango fechas | C108: Finanzas | D108: Descuentos comerciales | E108: Media | F108: Pendiente | G108: Calendario estable | J108: Ivan Cortes | K108: Liliana Preciado | L108: Fernando | O108: Proveedor – Indirectos | P108: 1.Abrir calendario | Q108: Medio | R108: Media | T108: Consulta | U108: FrontEnd
A109: DES 006 | B109: Validar colores de estatus Pendiente NC desde catálogo API | C109: Finanzas | D109: Descuentos comerciales | E109: Media | F109: Pendiente | G109: Colores correctos | J109: Ivan Cortes | K109: Liliana Preciado | L109: Fernando | O109: Analista Financiero – General | P109: 1.Ver grid | Q109: Medio | R109: Media | T109: Consulta | U109: FrontEnd
A110: DES 007 | B110: Validar formato fecha y moneda en NC relacionada | C110: Finanzas | D110: Descuentos comerciales | E110: Media | F110: Pendiente | G110: dd/mm/yyyy y $ correctos | J110: Ivan Cortes | K110: Liliana Preciado | L110: Fernando | O110: Analista Financiero – Especializado | P110: 1.Validar valores | Q110: Bajo | R110: Media | T110: Consulta | U110: FrontEnd
A111: DES 008 | B111: Validar paginación centrada con 10 registros exactos | C111: Finanzas | D111: Descuentos comerciales | E111: Media | F111: Pendiente | G111: Paginación centrada | J111: Ivan Cortes | K111: Liliana Preciado | L111: Fernando | O111: Gerente Financiero | P111: 1.Consultar | Q111: Medio | R111: Baja | T111: Consulta | U111: FrontEnd
A112: DES 009 | B112: Validar orden de columnas en grid descuento | C112: Finanzas | D112: Descuentos comerciales | E112: Media | F112: Pendiente | G112: Orden correcto columnas | J112: Ivan Cortes | K112: Liliana Preciado | L112: Fernando | O112: Gerente de Transporte | P112: 1.Validar grid | Q112: Medio | R112: Media | T112: Consulta | U112: FrontEnd
A113: DES 010 | B113: Persistencia filtros navegación en estatus NC relacionada | C113: Finanzas | D113: Descuentos comerciales | E113: Media | F113: Pendiente | G113: Filtros persistentes | J113: Ivan Cortes | K113: Liliana Preciado | L113: Fernando | O113: Comprador | P113: 1.Filtrar 2.Regresar | Q113: Alto | R113: Media | T113: Consulta | U113: FrontEnd
A114: DES 011 | B114: Mensaje UX sin resultados filtro documento inválido | C114: Finanzas | D114: Descuentos comerciales | E114: Media | F114: Pendiente | G114: Mensaje claro | J114: Ivan Cortes | K114: Liliana Preciado | L114: Fernando | O114: Gerente Comercial | P114: 1.Buscar inválido | Q114: Medio | R114: Alta | T114: Error | U114: FrontEnd
A115: DES 012 | B115: Consulta válida fecha+estatus Pendiente NC con descuentos sin relación | C115: Finanzas | D115: Descuentos comerciales | E115: Media | F115: Pendiente | G115: Registros correctos | J115: Ivan Cortes | K115: Liliana Preciado | L115: Fernando | O115: Proveedor – Mercancía | P115: 1.Filtrar | Q115: Alto | R115: Alta | T115: Consulta | U115: FrontEnd
A116: DES 013 | B116: Consulta documento exacto rebate específico en NC relacionada | C116: Finanzas | D116: Descuentos comerciales | E116: Media | F116: Pendiente | G116: Registro único correcto | J116: Ivan Cortes | K116: Liliana Preciado | L116: Fernando | O116: Proveedor – Transporte | P116: 1.Buscar doc | Q116: Alto | R116: Media | T116: Consulta | U116: FrontEnd
A117: DES 014 | B117: Consulta tipo rebate válido con múltiples resultados | C117: Finanzas | D117: Descuentos comerciales | E117: Media | F117: Pendiente | G117: Resultados consistentes | J117: Ivan Cortes | K117: Liliana Preciado | L117: Fernando | O117: Proveedor – Servicios | P117: 1.Filtrar rebate | Q117: Medio | R117: Media | T117: Consulta | U117: FrontEnd
A118: DES 015 | B118: Consulta proveedor restringido acceso a otros | C118: Finanzas | D118: Descuentos comerciales | E118: Media | F118: Pendiente | G118: Acceso denegado | J118: Ivan Cortes | K118: Liliana Preciado | L118: Fernando | O118: Proveedor – Indirectos | P118: 1.Intentar acceso | Q118: Alto | R118: Alta | T118: Restricción | U118: FrontEnd
A119: DES 016 | B119: Consulta rango fecha máximo 6 meses | C119: Finanzas | D119: Descuentos comerciales | E119: Media | F119: Pendiente | G119: Consulta permitida | J119: Ivan Cortes | K119: Liliana Preciado | L119: Fernando | O119: Analista Financiero – General | P119: 1.Filtrar rango | Q119: Medio | R119: Alta | T119: Consulta | U119: FrontEnd
... A125: DES 022 | B125: Ver descuentos aplicados en pantalla secundaria NC relacionada | C125: Finanzas | D125: Descuentos comerciales | E125: Media | F125: Pendiente | G125: Detalle correcto mostrado | J125: Ivan Cortes | K125: Liliana Preciado | L125: Fernando | O125: Proveedor – Mercancía | P125: 1.Ver detalle | Q125: Alto | R125: Media | T125: Consulta | U125: FrontEnd
A126: DES 023 | B126: Relacionar nota crédito válida Pendiente NC | C126: Finanzas | D126: Descuentos comerciales | E126: Media | F126: Pendiente | G126: Estatus pasa a NC relacionada | J126: Ivan Cortes | K126: Liliana Preciado | L126: Fernando | O126: Proveedor – Transporte | P126: 1.Relacionar NC | Q126: Alto | R126: Alta | S126: DES011 | T126: Actualización | U126: FrontEnd
A127: DES 024 | B127: Relacionar nota crédito desde pantalla secundaria | C127: Finanzas | D127: Descuentos comerciales | E127: Media | F127: Pendiente | G127: Relación exitosa | J127: Ivan Cortes | K127: Liliana Preciado | L127: Fernando | O127: Proveedor – Servicios | P127: 1.Ingresar pantalla 2.Relacionar | Q127: Alto | R127: Media | S127: DES011 | T127: Actualización | U127: FrontEnd
A128: DES 025 | B128: Cancelar descuento en Pendiente NC desde pantalla secundaria | C128: Finanzas | D128: Descuentos comerciales | E128: Media | F128: Pendiente | G128: Estatus cambia a cancelado | J128: Ivan Cortes | K128: Liliana Preciado | L128: Fernando | O128: Proveedor – Indirectos | P128: 1.Cancelar | Q128: Alto | R128: Media | S128: DES011 | T128: Actualización | U128: FrontEnd
A129: DES 026 | B129: Transición válida Pendiente NC→NC relacionada | C129: Finanzas | D129: Descuentos comerciales | E129: Media | F129: Pendiente | G129: Cambio correcto | J129: Ivan Cortes | K129: Liliana Preciado | L129: Fernando | O129: Analista Financiero – General | P129: 1.Relacionar NC | Q129: Alto | R129: Alta | S129: DES011 | T129: Actualización | U129: FrontEnd
A130: DES 027 | B130: Transición NC relacionada→Completado automático | C130: Finanzas | D130: Descuentos comerciales | E130: Media | F130: Pendiente | G130: Estatus 3 aplicado | J130: Ivan Cortes | K130: Liliana Preciado | L130: Fernando | O130: Analista Financiero – Especializado | P130: 1.Validar flujo | Q130: Alto | R130: Media | S130: DES025 | T130: Actualización | U130: FrontEnd
...

Sheet Listado Issue Abiertos
A1: Incidente | B1: Nivel | C1: Responsable | D1: Módulo | E1: Pantalla | F1: Revisión DEV | G1: Ajuste DEV | H1: Validado QA | I1: Comentario QA | J1: Fecha Reporte | K1: Fecha Resuelto
A2: Ajustar el documento PDF que se genera automáticamente cuando un proveedor no carga su nota de crédito. El campo «Folio Fiscal Relacionado» no está tomando el valor del elemento CfdiRelacionado (UUID). | B2: Medio | C2: Roberto | D2: Fiscal | E2: Notas de crédito | F2: x | G2: D | H2: x | J2: 46268
A3: Ajustar el proceso de sincronización de facturas y notas de crédito. En cada consulta, registrar la respuesta de SAP con los siguientes datos: documento SAP, mensaje y fecha contable del documento procesado. Si el registro no cambia de estatus, no volver a procesarlo, a fin de evitar información duplicada. | B3: Alto | C3: Roberto | D3: Fiscal | E3: Facturación | F3: x | G3: D | H3: 1 | J3: 46283
A4: Al cancelar una nota de crédito (NC), el cambio de estatus se realiza correctamente; sin embargo, falta implementar el siguiente flujo: cambiar a «Recibido parcial» el estatus de la factura relacionada y el de todas sus notas de crédito asociadas. | B4: Alto | C4: David | D4: Fiscal | E4: Notas de crédito | F4: x | H4: 1 | I4: Al intentar cancelar la NC marca error 403 21/09/2026 Aun no esta corregido. | J4: 46269
A5: Al cancelar una factura con estatus «Recibido parcial», cambiar automáticamente a «Cancelado» el estatus de todas las notas de crédito relacionadas y a «Disponible» el estatus de la recepción. Actualmente, este flujo está implementado. | B5: Alto | C5: David | D5: Fiscal | E5: Facturación | F5: x | H5: 1 | I5: Al intentar cancelar la NC marca error 403 | J5: 46284
A6: El estado de cuenta está incluyendo recepciones, facturas y notas de crédito canceladas. Estos documentos no deben mostrarse en el estado de cuenta. | B6: Alto | C6: Fernando | D6: Finanzas | E6: Estado de Cuenta | F6: x | G6: D | H6: x | I6: 21/09/2026 Ya se encuentra corregido, | J6: 46242
A7: Al cancelar una nota de crédito (NC), esta continúa considerándose en la sumatoria de la relación de la factura. Las notas de crédito canceladas no deben incluirse en dicha suma. | B7: Alto | C7: Fernando | D7: Fiscal | E7: Facturación | F7: x | G7: D | H7: x | J7: 46282
A8: Al intentar cargar un complemento de pago, el sistema muestra un error 403. | B8: Alto | C8: Fernando | D8: Fiscal | E8: Complemento Pago | F8: x | H8: 1 | J8: 46282
A9: Cuando un usuario inicia sesión por primera vez, revisar el macrorrol asignado para configurar de forma predeterminada el perfil genérico correspondiente y evitar que se muestre una pantalla en blanco. | B9: Alto | C9: Fernando | D9: Seguridad | E9: Seguridad | F9: x | G9: D | H9: 1 | J9: 46283
A10: En la pantalla de detalle de Carta Porte, el ID del usuario que realizó el registro se muestra como un valor numérico. Se debe mostrar el nombre del usuario. (Ocultar etiqueta) | B10: Bajo | C10: Fernando | D10: Finanzas | E10: Carta Porte | F10: x | G10: D | H10: x | J10: 46283
A11: En la pantalla de detalle, la información de las columnas «Número de documento» y «Documento SAP» está invertida. Además, quitar la columna «Fecha de actualización» para evitar que se muestre la barra de desplazamiento. | B11: Medio | C11: Fernando | D11: Finanzas | E11: Pagos | F11: x | G11: D | H11: x | J11: 46283
A12: En el reporte de detalle del pago, ajustar el nombre del archivo CSV al formato: detalle_pago_NumeroDocSAP_yyyymmdd.hh24mmss.csv. | B12: Bajo | C12: Fernando | D12: Finanzas | E12: Pagos | F12: x | G12: D | H12: x | I12: 25/09/2026 Corregido: pagos_20260925.105425 | J12: 46286
A13: Agregar la columna «Tipo de recepción» al proceso de descarga de recepciones de proveedores de mercancía. Consultar la historia de usuario: https://falabella.atlassian.net/browse/STM-1528. | B13: Alto | C13: Josue Lopez | D13: Finanzas | E13: Listado Recepciones | F13: x | H13: x | I13: Pendiente de validar | J13: 46273
A14: Ajustar el proceso de registro de recepciones de Carta Porte para publicar el tipo de recepción de los viajes. | B14: Alto | C14: Josue Lopez | D14: Finanzas | E14: Carta Porte | F14: x | H14: x | I14: Pendiente de validar | J14: 46283
A15: Crear el proceso para registrar los gastos adicionales generados en los viajes de los transportistas. | B15: Alto | C15: Josue Lopez | D15: Finanzas | E15: Carta Porte | F15: x | H15: Y | J15: 46283
A16: Agregar la columna «Tipo de recepción» a la notificación de recepciones pendientes de relacionar con una factura. (Colocar la descripción del tipo de recepción), validar que la recepción sean solo las disponibles (Revisar el back de recepciones) | B16: Alto | C16: Josue Lopez | D16: Finanzas | E16: Listado Recepciones | F16: x | H16: x | J16: 46283
A17: Con el usuario zedlav.sd87@gmail.com, al cambiar de institución o país, se siguen mostrando las tarjetas de México. | B17: Alto | C17: Oscar Bonelli | D17: Seguridad | E17: Seguridad | F17: x | G17: x | H17: x | I17: 21/09/2026 Se encuentra corregido. | J17: 46275
A18: Quitar la columna «Estatus de OC» de la pantalla y del reporte de Three Way Match. Además, el estatus de la recepción no coincide con el catálogo CatEstatusRecepcion. | B18: Alto | C18: Oscar Bonelli | D18: Finanzas | E18: Three way match | F18: x | G18: x | H18: x | J18: 46276
A19: En la pantalla de detalle de acuerdos comerciales no se muestra el nombre del proveedor; en su lugar, aparece el valor «ND». | B19: Bajo | C19: Oscar Bonelli | D19: Finanzas | E19: Descuentos Comercial | F19: x | G19: x | H19: x | I19: 21/09/2026 Se encuentra corregido. | J19: 46282
A20: Ajustar el nombre del archivo descargado del reporte de Three Way Match al siguiente formato: three_way_match_yyyymmdd.hh24mmss.csv o three_way_match_yyyymmdd.hh24mmss.xlsx, según corresponda. | B20: Bajo | C20: Oscar Bonelli | D20: Finanzas | E20: Three way match | F20: x | G20: x | H20: x | I20: 25/09/2026 Corregido Excel: three_way_match_20260925_122425 CSV: three_way_match_20260925_122523 | J20: 46283
A21: Quitar el grid de la nota de crédito y de la relación de factura, ya que la información se repite en el grid inferior. | B21: Bajo | C21: Oscar Bonelli | D21: Finanzas | E21: Descuentos Comercial | F21: x | G21: x | H21: x | I21: 21/09/2026 Aun no se encuentra corregido. 22/09/2026 Corregido. | J21: 46283
A22: Ajustar la pantalla de detalle del descuento comercial. Debajo de la relación de la nota de crédito, agregar un grid con las órdenes de compra que conforman el descuento comercial y las siguientes columnas: Orden de compra, Monto recibido, Fecha de recepción, Tipo de descuento y Monto de descuento. | B22: Alto | C22: Oscar Bonelli | D22: Finanzas | E22: Descuentos Comercial | F22: x | H22: 1
A23: Eliminar todos los catálogos cuyo nombre contenga «test» / «Prueba» y conservar únicamente los que se utilizarán en producción. Antes de eliminarlos, respaldar la información por si se identifican errores o relaciones con otros catálogos. | B23: Alto | C23: Ricardo | D23: Catálogo de Catálogos | E23: Catálogo de Catálogos | F23: x | G23: D | H23: x | I23: 21/09/2026 Validado, se encuentra corregido (QA). | J23: 46283
A24: Agregar la columna «Tipo de recepción». Consultar la historia de usuario: https://falabella.atlassian.net/browse/STM-1526. | B24: Alto | C24: Ricardo | D24: Finanzas | E24: Recepciones MIGO | F24: x | G24: D | H24: 1 | J24: 46279
A25: [Funcional][Control de acceso - Rol/Atributo] Implementar la gestión y asignación de atributos por rol, en sustitución de la administración por usuario. | B25: Alto | C25: Ricardo | D25: Seguridad | E25: Seguridad | F25: x | G25: x | H25: x | I25: Se validan correctamente los Criterios de Aceptación en ambiente QA el 24/09/2026. El comportamiento cumple con el resultado esperado. Se procede a cerrar el ticket. | J25: 46274 | K25: 46289
A26: [Funcional][Seguridad / Rol Atributo] No permite seleccionar valores de los atributos de segmentación | B26: Alto | C26: Ricardo | D26: Seguridad | E26: Seguridad | F26: x | G26: 1 | H26: 1 | I26: Ya se muestra la lista desplegable de cada atributo. Falta validar que también se despliegue para «Empresa», «Grupo proveedor» y «Tipo rebate», además de ajustar aspectos de UX/UI. También se validó el filtrado de datos con el atributo «Tipo proveedor = Transporte», pero aún no funciona. | J26: 46269
A27: [Backend][Global: Control de Acceso] Eventos relacionados con permisos incorrectos permiten ejecutar acciones no autorizadas | B27: Alto | C27: Ricardo | D27: Seguridad | E27: Seguridad | F27: x | G27: 1 | H27: 1 | I27: El catálogo «Permiso» ha sido modificado y homologado, adicionalmente que la matriz de de "Catálogos x Permisos" ha sido subida al ticket de Jira para que se aplique la actualización correspondiente. | J27: 46269
A28: [Funcional][Catálogos: Elementos] Filtro "Catálogo Padre" muestra catálogos sin relación con el catálogo consultado | B28: Medio | C28: Ricardo | D28: Catálogo de Catálogos | E28: Catálogo de Catálogos | F28: x | G28: x | H28: x | I28: Se validan correctamente los Criterios de Aceptación en ambiente QA el 21/09/2026. El comportamiento cumple con el resultado esperado. Se procede a cerrar el ticket. | J28: 46286
A29: [Funcional][Catálogos: Conversiones] La consulta no muestra en el grid las fechas de inicio y fin de los elementos de conversión | B29: Bajo | C29: Ricardo | D29: Catálogo de Catálogos | E29: Catálogo de Catálogos | F29: x | G29: x | H29: x | I29: Se validan correctamente los Criterios de Aceptación en ambiente QA el 21/09/2026. El comportamiento cumple con el resultado esperado. Se procede a cerrar el ticket. | J29: 46286
A30: Revisar los xml de recepciones debido a error de parcero en el proceso de registro de recepciones en FBC | B30: Alto | C30: Josue Lopez | D30: Finanzas | E30: Listado Recepciones | F30: x | H30: x | J30: 46283
A31: No se visualizan las facturas pendientes de pago en el estado de cuenta, proveedor trabicel | B31: Alto | C31: Fernando | D31: Finanzas | E31: Estado de Cuenta | F31: x | G31: D | H31: 1 | I31: 21/09/2026 Se encuentra coregido. | J31: 46286
A32: Recepciones migo no sigue formato de descarga CSV, se guarda de esta manera: recepciones-migo-MIGO-20260918-003612306_20260921_15.53.20 | B32: Bajo | C32: Ricardo | D32: Finanzas | E32: Recepciones MIGO | F32: x | G32: D | H32: x | I32: 23/09/2026 Se encuentra corregido. | J32: 46286
A33: CSV de cátalo de usuarios descarga con este nombre: catalogo-usuarios-21-09-2026-16-26 debería considerar formato nombre_yyyymmdd.hh24mmss | B33: Bajo | C33: Ricardo | D33: Seguridad | E33: Catálogo de Catálogos | F33: x | G33: D | H33: 1 | J33: 46286
A34: CSV de Aplicativo Evento descarga con este nombre: aplicativo-evento-21-09-2026-16-31 debería considerar formato nombre_yyyymmdd.hh24mmss | B34: Bajo | C34: Ricardo | D34: Seguridad | E34: Seguridad | F34: x | G34: D | H34: x | I34: 23/09/2026 Se encuentra corregido. | J34: 46286
A35: CSV de Perfil Aplicativo descarga con este nombre: perfil-aplicativo-21-09-2026-16-32 debería considerar formato nombre_yyyymmdd.hh24mmss | B35: Bajo | C35: Ricardo | D35: Seguridad | E35: Seguridad | F35: x | G35: D | H35: x | I35: 23/09/2026 Se encuentra corregido. | J35: 46286
A36: En cualquier opción de Control de Acceso permite seleccionar fechas con días posteriores | B36: Bajo | C36: Ricardo | D36: Seguridad | E36: Seguridad | F36: x | G36: D | H36: x | J36: 46286
A37: Inicio/Herramientas y Utilerías/Configuración de Parámetros: el nombre en la descarga en formato Excel y CSV, no se guarda de acuerdo con el formato: nombre_yyyymmdd.hh24mmss Excel: parametros_20260922_0810.xlsx CSV: parametros_20260922_0811.csv | B37: Bajo | C37: Ricardo | D37: Catálogo de Catálogos | E37: Catálogo de Catálogos | G37: D | H37: x | J37: 46287
A38: Inicio/Herramientas y Utilerías/Gestión de Catálogos/Proveedores: el nombre en la descarga en formato Excel y CSV, no se guarda de acuerdo con el formato: nombre_yyyymmdd.hh24mmss Excel: proveedores_2026-09-22.xlsx CSV: proveedores_2026-09-22.csv | B38: Bajo | C38: Ricardo | D38: Catálogo de Catálogos | E38: Catálogo de Catálogos | G38: D | H38: 1 | J38: 46287
A39: Inicio/Herramientas y Utilerías/Gestión de Catálogos/Bloqueo de Proveedores: el nombre en la descarga en formato Excel y CSV, no se guarda de acuerdo con el formato: nombre_yyyymmdd.hh24mmss Excel: bloqueos_proveedores_2026-09-22.xlsx CSV: bloqueos_proveedores_2026-09-22.csv | B39: Bajo | C39: Ricardo | D39: Catálogo de Catálogos | E39: Catálogo de Catálogos | G39: D | H39: 1 | J39: 46287
A40: Inicio/Herramientas y Utilerías/Gestión de Catálogos/Catálogos: el nombre en la descarga en formato Excel y CSV, no se guarda de acuerdo con el formato: nombre_yyyymmdd.hh24mmss Excel: catalogos_20260922143201.xlsx CSV: catalogos_20260922143136.csv | B40: Bajo | C40: Ricardo | D40: Catálogo de Catálogos | E40: Catálogo de Catálogos | G40: D | H40: 1 | J40: 46287
A41: Inicio/Herramientas y Utilerías/Bitácora de Actividades: se muestra mensaje de error: Error Error exportando CSV, al intentar realizar la descarga. | B41: Bajo | C41: Ricardo | D41: Catálogo de Catálogos | E41: Catálogo de Catálogos | G41: D | H41: 1 | J41: 46287
A42: Inicio/Herramientas y Utilerías: no es visible el recuadro de: Estado de conexión. | B42: Bajo | C42: Ricardo | D42: Catálogo de Catálogos | E42: Catálogo de Catálogos | G42: D | H42: 1 | J42: 46287
A43: Inicio>Finanzas>Guías de Embarque, la descarga de la Carta Porte, en formato XML y CSV, no se guarda en formato correcto: nombre_yyyymmdd.hh24mmss XML: Carta_Porte_ABASTO_379EX215092026202610.xml CSV: Carta_Porte_ABASTO_379EX215092026202610.csv | B43: Bajo | C43: Fernando | D43: Finanzas | E43: Carta Porte | H43: x | I43: No aplica el cambio es correcto el formato que tiene | J43: 46287
A44: Los asignación/desasignación de nuevos eventos de agregados de la pantalla "Conversiones" en el Módulo de Catálogos no están funcionando correctamente, se debe generar o arreglar la relación con los componentes. | B44: Alto | C44: Ricardo | D44: Seguridad | E44: Seguridad | F44: 1 | G44: D | H44: 1 | J44: 46288
A45: Inicio>Fiscal>Facturas, al exportar el Listado de facturas a CSV, se guarda de la siguiente manera: factura_20260923_09.45.59 No cumple con el formato: nombre_modulo_yyyymmdd.h24miss.csv. | B45: Bajo | C45: Fernando | D45: Fiscal | E45: Facturación | G45: D | H45: x | I45: Ajustado 25/09/2026 Corregido: factura_20260925.105001 | J45: 46288
A46: Inicio>Fiscal>Facturas, al exportar XML y PDF de la factura, se guarda de la siguiente manera: XML: 9101027130-20260923.0950 PDF: 9101027130-20260923.0950 No cumple con el formato: nombre_modulo_yyyymmdd.h24miss.csv. | B46: Bajo | C46: Fernando | D46: Fiscal | E46: Notas de crédito | F46: x | G46: D | H46: x | I46: 25/09/2026 Corregido Excel: factura_20260925.125511 PDF: factura_20260925.125724 | J46: 46288
A47: Inicio>Fiscal>Notas de Crédito, al exportar el Listado de notas de crédito a CSV, se guarda de la siguiente manera: nota_credito_20260923_09.54.00 No cumple con el formato: nombre_modulo_yyyymmdd.h24miss.csv. | B47: Bajo | C47: Fernando | D47: Fiscal | E47: Notas de crédito | F47: x | G47: D | H47: x | I47: 25/09/2026 Parcialmente corregido: El nombre del archivo al exportar se genera correctamente: nota_credito_20260925.130533 Sin embargo, el horario se mantiene para las proximas exportaciones | J47: 46288
A48: Inicio>Fiscal>Notas de Crédito, al exportar XML y PDF de la nota de crédito, se guarda de la siguiente manera: XML: a252062a-bd50-49c6-86c9-800c3bf3c0bf PDF: AA-73304-20260923.1004 No cumple con el formato: nombre_modulo_yyyymmdd.h24miss.csv. | B48: Bajo | C48: Fernando | D48: Fiscal | E48: Notas de crédito | F48: x | G48: D | H48: x | I48: 25/09/2026 Corregido: XML: nota_credito_20260925.131239 PDF: nota_credito_20260925.131316 | J48: 46288
A49: Inicio>Finanzas>Pagos, al exportar el Listado de pagos a CSV, se guarda de la siguiente manera: pagos_20260923_16.03.55 No cumple con el formato: nombre_modulo_yyyymmdd.h24miss.csv. | B49: Bajo | C49: Fernando | D49: Finanzas | E49: Pagos | F49: x | G49: D | H49: x | I49: 25/09/2026 Se encuentra corregido: pagos_20260925.102439 | J49: 46288

Sheet Carga por Responsable
A1: CARGA DE INCIDENCIAS POR RESPONSABLE
A2: 48 incidencias abiertas · desglose por nivel de complejidad
A3: Responsable | B3: Total asignado | C3: Alto | D3: Medio | E3: Bajo | F3: Cerrados | G3: Pendientes
A4: Ricardo | B4: =COUNTIF('Listado Issue Abiertos'!$C$2:$C$217,$A4) -> 19 | C4: =COUNTIFS('Listado Issue Abiertos'!$C$2:$C$217,$A4,'Listado Issue Abiertos'!$B$2:$B$217,C$3) -> 6 | D4: =COUNTIFS('Listado Issue Abiertos'!$C$2:$C$217,$A4,'Listado Issue Abiertos'!$B$2:$B$217,D$3) -> 1 | E4: =COUNTIFS('Listado Issue Abiertos'!$C$2:$C$217,$A4,'Listado Issue Abiertos'!$B$2:$B$217,E$3) -> 12 | F4: 9 | G4: =tblCargaResponsable[[#This Row],[Total asignado]]-tblCargaResponsable[[#This Row],[Cerrados]] -> 10
A5: Fernando | B5: =COUNTIF('Listado Issue Abiertos'!$C$2:$C$217,$A5) -> 14 | C5: =COUNTIFS('Listado Issue Abiertos'!$C$2:$C$217,$A5,'Listado Issue Abiertos'!$B$2:$B$217,C$3) -> 5 | D5: =COUNTIFS('Listado Issue Abiertos'!$C$2:$C$217,$A5,'Listado Issue Abiertos'!$B$2:$B$217,D$3) -> 1 | E5: =COUNTIFS('Listado Issue Abiertos'!$C$2:$C$217,$A5,'Listado Issue Abiertos'!$B$2:$B$217,E$3) -> 8 | F5: 11 | G5: =tblCargaResponsable[[#This Row],[Total asignado]]-tblCargaResponsable[[#This Row],[Cerrados]] -> 3
A6: Oscar Bonelli | B6: =COUNTIF('Listado Issue Abiertos'!$C$2:$C$217,$A6) -> 6 | C6: =COUNTIFS('Listado Issue Abiertos'!$C$2:$C$217,$A6,'Listado Issue Abiertos'!$B$2:$B$217,C$3) -> 3 | D6: =COUNTIFS('Listado Issue Abiertos'!$C$2:$C$217,$A6,'Listado Issue Abiertos'!$B$2:$B$217,D$3) -> 0 | E6: =COUNTIFS('Listado Issue Abiertos'!$C$2:$C$217,$A6,'Listado Issue Abiertos'!$B$2:$B$217,E$3) -> 3 | F6: 5 | G6: =tblCargaResponsable[[#This Row],[Total asignado]]-tblCargaResponsable[[#This Row],[Cerrados]] -> 1
A7: Josue Lopez | B7: =COUNTIF('Listado Issue Abiertos'!$C$2:$C$217,$A7) -> 5 | C7: =COUNTIFS('Listado Issue Abiertos'!$C$2:$C$217,$A7,'Listado Issue Abiertos'!$B$2:$B$217,C$3) -> 5 | D7: =COUNTIFS('Listado Issue Abiertos'!$C$2:$C$217,$A7,'Listado Issue Abiertos'!$B$2:$B$217,D$3) -> 0 | E7: =COUNTIFS('Listado Issue Abiertos'!$C$2:$C$217,$A7,'Listado Issue Abiertos'!$B$2:$B$217,E$3) -> 0 | F7: 5 | G7: =tblCargaResponsable[[#This Row],[Total asignado]]-tblCargaResponsable[[#This Row],[Cerrados]] -> 0
A8: Roberto | B8: =COUNTIF('Listado Issue Abiertos'!$C$2:$C$217,$A8) -> 2 | C8: =COUNTIFS('Listado Issue Abiertos'!$C$2:$C$217,$A8,'Listado Issue Abiertos'!$B$2:$B$217,C$3) -> 1 | D8: =COUNTIFS('Listado Issue Abiertos'!$C$2:$C$217,$A8,'Listado Issue Abiertos'!$B$2:$B$217,D$3) -> 1 | E8: =COUNTIFS('Listado Issue Abiertos'!$C$2:$C$217,$A8,'Listado Issue Abiertos'!$B$2:$B$217,E$3) -> 0 | F8: 1 | G8: =tblCargaResponsable[[#This Row],[Total asignado]]-tblCargaResponsable[[#This Row],[Cerrados]] -> 1
A9: David | B9: =COUNTIF('Listado Issue Abiertos'!$C$2:$C$217,$A9) -> 2 | C9: =COUNTIFS('Listado Issue Abiertos'!$C$2:$C$217,$A9,'Listado Issue Abiertos'!$B$2:$B$217,C$3) -> 2 | D9: =COUNTIFS('Listado Issue Abiertos'!$C$2:$C$217,$A9,'Listado Issue Abiertos'!$B$2:$B$217,D$3) -> 0 | E9: =COUNTIFS('Listado Issue Abiertos'!$C$2:$C$217,$A9,'Listado Issue Abiertos'!$B$2:$B$217,E$3) -> 0 | F9: 0 | G9: =tblCargaResponsable[[#This Row],[Total asignado]]-tblCargaResponsable[[#This Row],[Cerrados]] -> 2
A11: TOTAL GENERAL | B11: =SUM(B4:B9) -> 48 | C11: =SUM(C4:C9) -> 22 | D11: =SUM(D4:D9) -> 3 | E11: =SUM(E4:E9) -> 23 | F11: =SUM(F4:F9) -> 31 | G11: =SUM(G4:G9) -> 17

Sheet Total
A3: Etiquetas de fila | B3: Suma de Validado QA
A4: Carta Porte | B4: 0
A5: Catálogo de Catálogos | B5: 6
A6: Complemento Pago | B6: 1
A7: Descuentos Comercial | B7: 1
A8: Estado de Cuenta | B8: 1
A9: Facturación | B9: 2
A10: Listado Recepciones | B10: 0
A11: Notas de crédito | B11: 1
A12: Pagos | B12: 0
A13: Recepciones MIGO | B13: 1
A14: Seguridad | B14: 4
A15: Three way match | B15: 0
A16: (en blanco)
A17: Total general | B17: 17

Sheet Presentacion
A1: Opciones | B1: Total Escenarios | C1: Total Validados | D1: Porcentaje Validado | E1: Issue Abiertos
A2: Listado Recepciones | B2: 51 | C2: 51 | D2: =(C2/B2) -> 1 | E2: =VLOOKUP(A2,Total!$A$4:$B$25,2,FALSE) -> 0
A3: Carta Porte | B3: 50 | C3: 50 | D3: =(C3/B3) -> 1 | E3: =VLOOKUP(A3,Total!$A$4:$B$25,2,FALSE) -> 0
A4: Recepciones MIGO | B4: 52 | C4: 52 | D4: =(C4/B4) -> 1 | E4: =VLOOKUP(A4,Total!$A$4:$B$25,2,FALSE) -> 1
A5: Estado de cuenta | B5: 49 | C5: 41 | D5: =(C5/B5) -> 0.83673469 | E5: =VLOOKUP(A5,Total!$A$4:$B$25,2,FALSE) -> 1
A6: Three way match | B6: 50 | C6: 50 | D6: =(C6/B6) -> 1 | E6: =VLOOKUP(A6,Total!$A$4:$B$25,2,FALSE) -> 0
A7: Pagos | B7: 49 | C7: 49 | D7: =(C7/B7) -> 1 | E7: =VLOOKUP(A7,Total!$A$4:$B$25,2,FALSE) -> 0
A8: Descuentos Comercial | B8: 49 | C8: 45 | D8: =(C8/B8) -> 0.91836735 | E8: =VLOOKUP(A8,Total!$A$4:$B$25,2,FALSE) -> 1
A9: Facturación | B9: 47 | C9: 47 | D9: =(C9/B9) -> 1 | E9: =VLOOKUP(A9,Total!$A$4:$B$25,2,FALSE) -> 2
A10: Notas de Crédito | B10: 48 | C10: 48 | D10: =(C10/B10) -> 1 | E10: =VLOOKUP(A10,Total!$A$4:$B$25,2,FALSE) -> 1
A11: Complemento Pago | B11: 48 | C11: 48 | D11: =(C11/B11) -> 1 | E11: =VLOOKUP(A11,Total!$A$4:$B$25,2,FALSE) -> 1
A12: Catálogo de catálogos | B12: 177 | C12: 177 | D12: =(C12/B12) -> 1 | E12: =VLOOKUP(A12,Total!$A$4:$B$25,2,FALSE) -> 6
A13: Configuración de parámetros | B13: 101 | C13: 101 | D13: =(C13/B13) -> 1 | E13: 0
A14: Seguridad | B14: 50 | C14: 50 | D14: =(C14/B14) -> 1 | E14: =VLOOKUP(A14,Total!$A$4:$B$25,2,FALSE) -> 4
A15: Total | B15: =SUM(B2:B14) -> 821 | C15: =SUM(C2:C14) -> 809 | D15: =(C15/B15) -> 0.98538368 | E15: =SUM(E2:E14) -> 17

Sheet CatModulo
A1: Modulo | B1: Finanzas | C1: Fiscal | D1: Utilerias | E1: Prioridad | F1: Estado | G1: Responsable Dev | H1: Responsable QA | I1: Responsable UAT | J1: Impacto | K1: Probabilidad | L1: Tipo
A2: Finanzas | B2: Recepciones | C2: Facturación | D2: Catálogos | E2: Critico | F2: Pasó | G2: David Montes | H2: Marco Vezquez | I2: Nelva Flores | J2: Alto | K2: Alta | L2: BackEnd
A3: Fiscal | B3: Carta Porte | C3: Notas de crédito | D3: Gestión de seguridad | E3: Alta | F3: Falló | G3: Oscar Bonelli | H3: Saul Valdez | I3: Diana Hernandez | J3: Medio | K3: Media | L3: Batch
A4: Utilerias | B4: Recepciones MIGO | C4: Complemento de pago | D4: Auditoria | E4: Media | F4: En Progreso | G4: Fernando | H4: Paola Leon | I4: Liliana Preciado | J4: Bajo | K4: Baja | L4: FrontEnd
B5: Estado de cuenta | D5: Configuración de Parámetros | E5: Baja | F5: Pendiente | G5: Ricardo | H5: Ivan Cortes | L5: ETL
B6: Three way match | F6: Bloqueado | G6: Josue Lopez | H6: Alexis Gines
B7: Pagos | H7: Daniel Moreno
B8: Descuentos comerciales

Sheet Instrucciones
A1: 📋 GUÍA DE USO – MATRIZ DE SEGUIMIENTO DE PRUEBAS
A3: CAMPO | B3: DESCRIPCIÓN | C3: VALORES PERMITIDOS
A4: ID | B4: Identificador único del escenario. Formato: TC-XXX | C4: TC-001, TC-002…
A5: Escenario de Prueba | B5: Descripción clara y concisa del caso de prueba | C5: Texto libre
A6: Módulo | B6: Módulo principal del sistema al que pertenece | C6: Ej: Autenticación
A7: Submódulo | B7: Componente específico dentro del módulo | C7: Ej: Login, Logout
A8: Prioridad | B8: Nivel de criticidad del escenario | C8: Alta / Media / Baja
A9: Estado | B9: Estado actual de la ejecución del escenario | C9: Ver tabla de estados
A10: Resultado Esperado | B10: Comportamiento esperado según los criterios de aceptación | C10: Texto libre
A11: Resultado Obtenido | B11: Comportamiento real observado durante la ejecución | C11: Texto libre
A12: Vinculación Bug | B12: ID del bug en Jira si el escenario falló; '-' si no aplica | C12: STM-XXXX o -
A13: Responsable QA | B13: Nombre del QA asignado a este escenario | C13: Nombre del tester
A14: Responsable Negocio (UAT) | B14: Nombre del responsable del equipo de negocio | C14: Nombre Owner
A18: LEYENDA DE ESTADOS
A19: Pendiente | B19: El escenario aún no ha sido ejecutado
A20: En Progreso | B20: El escenario está siendo ejecutado
A21: Pasó | B21: El escenario fue ejecutado exitosamente
A22: Falló | B22: El resultado no coincidió con lo esperado
A23: Bloqueado | B23: No se puede ejecutar por un impedimento

Sheet Listado Issue Abiertos_v1.0
A1: Incidente | B1: Nivel | C1: Responsable | D1: Modulo | E1: Pantalla | F1: Revisión DEV | G1: Ajuste DEV | H1: Validado QA | I1: Comentario QA | J1: Fecha Reporte | K1: Fecha Resuelto
A2: En la pantalla de bitacora de actividades tiene el link de auditoria el cual no funciona, para este caso solo debe llevar a Inicio -> Herramientas y Utilerias -> Bitacora de Actividades | B2: Bajo | C2: Roberto | D2: Auditoria | E2: Bitacora de actividades | F2: x | G2: x | H2: x | I2: Validado por QA 23/06/2026 corregido.
A3: El diseño de la pantalla de Bitacora de actividades se distorsiono considerando el layout de todas las pantallas que se han trabajado | B3: Bajo | C3: Roberto | D3: Auditoria | E3: Bitacora de actividades | F3: x | G3: x | H3: x | I3: Validado por QA 23/06/2026 corregido.
A4: Cambiar el formato para descargar los reportes de Excel y CSV colocarlos en formato de botón secundario del lado izquierdo del botón de bloqueo de proveedores | B4: Bajo | C4: Ricardo | D4: Utilerias | E4: Bloqueo de proveedores | F4: x | G4: x | H4: x | I4: Validado por QA 23/06/2026 corregido.
A5: No permitir cargar la data solo hasta que el usuario seleccione los filtros de busqueda | B5: Bajo | C5: Roberto | D5: Utilerias | E5: Bloqueo de proveedores | F5: x | G5: x | H5: x | I5: Validado por QA 23/06/2026 corregido.
A6: El botón de buscar colocarlo al lado izquierdo del campo de busqueda Estatus y el link de limpar colocarlo a lado derecho del botón de buscar ademas de cambiarlo a botón secundarios | B6: Bajo | C6: Roberto | D6: Utilerias | E6: Bloqueo de proveedores | F6: x | G6: x | H6: x | I6: Validado por QA 23/06/2026 corregido.
A7: La pantalla de Catálogo de Catálogos no tiene el filtro de busqueda inicial presentando el grid de consulta y la distribución de los botones el botón de buscar colocarlo a la izquieda y el botón de limpiar a la derecha ademas de colocarlo en formato de botón | B7: Bajo | C7: Roberto | D7: Catálogo de catálogos | E7: Catálogo de catálogos | F7: x | G7: x | H7: x | I7: Validado por QA 23/06/2026 corregido.
A8: El link de volver en la pagina de catálogo de catálogos enviarlo a la derecha | B8: Bajo | C8: Roberto | D8: Utilerias | E8: Catálogo de catálogos | F8: x | G8: x | H8: x | I8: Validado por QA 23/06/2026 corregido.
A9: Los botones de Exportar a CSV y Excel dejarlos visible pero inactivos cuando no exista data, cuando retorne resultado el grid activar los botones | B9: Bajo | C9: Roberto | D9: Utilerias | E9: Catálogo de catálogos | F9: x | G9: x | H9: x | I9: Validado por QA 23/06/2026 corregido.
A10: Marca error de query al intentar agregar un nuevo evento en la pantalla "Catálogo de catálogo" | B10: Alto | C10: Ricardo | D10: Utilerias | E10: Catálogo de catálogos | F10: x | G10: x | H10: x | I10: Validado por QA 23/06/2026 corregido.
A11: Cambiar el formato para descargar los reportes de Excel y CSV colocarlos en formato de botón secundario del lado izquierdo del botón de catálogo de proveedores | B11: Bajo | C11: Roberto | D11: Utilerias | E11: Catálogo de proveedores | F11: x | G11: x | H11: x | I11: Validado por QA 23/06/2026 corregido.
A12: El botón de buscar colocarlo al lado izquierdo del campo de busqueda Estatus y el link de limpar colocarlo a lado derecho del botón de buscar ademas de cambiarlo a botón secundarios | B12: Bajo | C12: Roberto | D12: Utilerias | E12: Catálogo de proveedores | F12: x | G12: x | H12: x | I12: Validado por QA 23/06/2026 corregido.
A13: No permitir cargar la data solo hasta que el usuario seleccione los filtros de busqueda | B13: Bajo | C13: Roberto | D13: Utilerias | E13: Catálogo de proveedores | F13: x | G13: x | H13: x | I13: Validado por QA 23/06/2026 corregido.
... A15: Los Link del flujo de pantallas no funcionan en la pantalla y tampoco redirecciona al home Configuración de Parámetros | B15: Bajo | C15: Roberto | D15: Utilerias | E15: Configuración de parámetros | F15: x | G15: x | H15: x | I15: Validado por QA 23/06/2026 corregido.
A16: Agregar una columna en la addenda de la NC indicando si viene de un descuento comercial o ajuste por recepción 2 - Descuento Comercial | B16: Alto | C16: David | D16: Finanzas | E16: Descuentos Comercial | F16: x | G16: x | H16: x
A17: Cuando selecciona la opción de "Todos los tipos" en el listbox de "Tipo Rebate" no retorna nada, cuando se deja en blanco el tipo de rebate retorna resultado | B17: Medio | C17: Fernando | D17: Finanzas | E17: Descuentos Comercial | F17: x | G17: x | H17: x | I17: Validado por QA 23/06/2026 corregido.
A18: Cuando selecciona la opción de "Todos los tipos" en el listbox de estatus no retorna nada, cuando se deja en blanco el tipo de rebate retorna resultado | B18: Medio | C18: Fernando | D18: Finanzas | E18: Descuentos Comercial | F18: x | G18: x | H18: x | I18: Validado por QA 24/06/2026 corregido.
A19: El botón de buscar en el estado de cuenta se debe presentar como botón primario | B19: Bajo | C19: Oscar Bonelli | D19: Finanzas | E19: Estado de cuenta | F19: x | G19: x | H19: x | I19: Validado por QA 24/06/2026 corregido.
A20: La paginación en el estado de cuenta no esta funcionando | B20: Bajo | C20: Oscar Bonelli | D20: Finanzas | E20: Estado de cuenta | F20: x | G20: x | H20: x | I20: La paginación aplica hasta dar una segunda selección de los registros a visualizar
A21: En el grid de consulta el nombre del proveedor no se visualiza, considerando que se encuentra catálogado, el ejemplo es el proveedor 34786 | B21: Medio | C21: Fernando | D21: Finanzas | E21: Descuentos Comercial | F21: x | G21: x | H21: x | I21: Validado por QA 24/06/2026 corregido.
A22: Cuando se realiza la busqueda por proveedor, no retorna la información de los datos que estan relacionados | B22: Medio | C22: Fernando | D22: Finanzas | E22: Descuentos Comercial | F22: x | G22: x | H22: x | I22: Validado por QA 24/06/2026 corregido.
A23: El boton de limpiar no deja en blanco los parametros de busqueda | B23: Medio | C23: Fernando | D23: Finanzas | E23: Estado de cuenta | F23: x | G23: x | H23: x | I23: Validado por QA 25/06/2026 corregido.
A24: Cuando se busca un mes y no existe información, presentar una modal de alerta indicando que no existe información en el periodo consultado | B24: Medio | C24: Fernando | D24: Finanzas | E24: Estado de cuenta | F24: x | G24: x | H24: x | I24: Validado por QA 24/06/2026 corregido.
A25: No se visualiza el nombre del proveedor considerando que se encuentra dado de alta en el catálogo de proveedores | B25: Medio | C25: Fernando | D25: Finanzas | E25: Estado de cuenta | F25: x | G25: x | H25: x | I25: Validado por QA 24/06/2026 corregido.
A26: Marca error de consulta cuando seleccionamos el mes en el estado de cuenta | B26: Medio | C26: Fernando | D26: Finanzas | E26: Estado de cuenta | F26: x | G26: x | H26: x | I26: Validado por QA 25/06/2026 corregido.
A27: El calendario de busqueda en la pagina de facturación se pierde el mes y año en que se encuentra ademas es complejo operarlo | B27: Bajo | C27: Oscar Bonelli | D27: Fiscal | E27: Facturación | F27: x | G27: x | H27: x | I27: Validado por QA 25/06/2026 corregido.
A28: El tipo de proveedor no se visualiza en el grid de consulta de facturación cuando se hace un cambio en el catálogo de tipo de proveedores | B28: Medio | C28: David | D28: Fiscal | E28: Facturación | F28: x | G28: x | H28: x | I28: Validado por QA 25/06/2026 corregido.
... A30: El filtro de busqueda de las facturas esta retornando información de otros días de consulta | B30: Alto | C30: David | D30: Fiscal | E30: Facturación | F30: x | G30: x | H30: x | I30: Validado por QA 25/06/2026 corregido.
A31: No se visualiza el PDF publicado de la factura, marca error al intentar abrir el archivo | B31: Alto | C31: David | D31: Fiscal | E31: Facturación | F31: x | G31: x | H31: x
A32: Cuando se publica una factura la fecha de recepción esta considerando otro dato, lo que se espera es que se registre con la fecha actual del registro de la factura | B32: Alto | C32: David | D32: Fiscal | E32: Facturación | F32: x | G32: x | H32: x
A33: El botón de cancelar factura debera estar activo cuando se encuentre en los siguientes estatus: 3 - En proceso envio 6 - Error en el desglose de la factura 16 - Estructura invalida | B33: Alto | C33: Fernando | D33: Fiscal | E33: Facturación | F33: x | G33: x | H33: x | I33: Continua presentado los iconos para cancelar la factura
A34: Ajustar el texto principal de la tarjeta de finanzas por Operaciones -> Gestión de recepciones, pagos y descuentos | B34: Bajo | C34: Oscar Bonelli | D34: Finanzas | E34: Finanzas | F34: x | G34: x | H34: x | I34: Validado por QA 25/06/2026 corregido.
A35: Colocar en la parte superior de los grid de consulta el numero de registro que retorna la consulta en las siguientes pantallas Recepciones Guías de embarque Descuentos Comerciales Recepciones MIGO Estado de cuenta Three way match | B35: Bajo | C35: Oscar Bonelli | D35: Finanzas | E35: Finanzas | F35: x | G35: x | H35: x
A36: Ajustar el texto principal de la tarjeta de fiscal por Cuéntanos, ¿Qué necesitas? -> Gestión de documentación fiscal | B36: Bajo | C36: Oscar Bonelli | D36: Fiscal | E36: Fiscal | F36: x | G36: x | H36: x | I36: Validado por QA 25/06/2026 corregido.
A37: Colocar en la parte superior de los grid de consulta el numero de registro que retorna la consulta en las siguientes pantallas Facturacion Notas de Crédito Complemento pago | B37: Bajo | C37: Oscar Bonelli | D37: Fiscal | E37: Fiscal | F37: x | G37: x | H37: x
A38: El calendario de busqueda en la pagina de notas de crédito se pierde el mes y año en que se encuentra ademas es complejo operarlo | B38: Bajo | C38: Oscar Bonelli | D38: Fiscal | E38: Notas de crédito | F38: x | G38: x | H38: x | I38: Validado por QA 25/06/2026 corregido.
A39: En la pantalla de notas de crédito dejar un solo botón primario, el botón de Exportar CSV cambiarlo a blanco, | B39: Bajo | C39: Oscar Bonelli | D39: Fiscal | E39: Notas de crédito | F39: x | G39: x | H39: x | I39: Validado por QA 29/06/2026 corregido.
A40: El tipo de proveedor no se visualiza en el grid de consulta de notas de crédito cuando se hace un cambio en el catálogo de tipo de proveedores | B40: Medio | C40: David | D40: Fiscal | E40: Notas de crédito | F40: x | G40: x | H40: x
A41: El filtro de busqueda de las notas de crédito esta retornando información de otros días de consulta | B41: Alto | C41: David | D41: Fiscal | E41: Notas de crédito | F41: x | G41: x | H41: x
A42: Filtrar la condición de pago permitidas para dar de alta una nota de crédito | B42: Alto | C42: David | D42: Fiscal | E42: Notas de crédito | F42: x | G42: x | H42: x
A43: Agregar una columna en la addenda de la NC indicando si viene de un descuento comercial o ajuste por recepción 1 - Ajuste por recepción | B43: Alto | C43: David | D43: Fiscal | E43: Notas de crédito | F43: x | G43: x | H43: x
A44: Marca error de archivo XML obligatorio cuando existe registrado previamente | B44: Medio | C44: Fernando | D44: Finanzas | E44: Listado Recepciones | F44: x | G44: x | H44: x
A45: No valida el bloqueo de proveedores por tipo de proveedor | B45: Alto | C45: Fernando | D45: Finanzas | E45: Listado Recepciones | F45: x | G45: x | H45: x
A46: El cambio de estatus de la recepción a manual no se actualiza, revisar que permita cambiar a "Consumida Manual" y validar si guardamos la información del uuid en una tabla alterna, validar que no exista el uuid registrado previamente en el modulo fiscal | B46: Alto | C46: Fernando | D46: Finanzas | E46: Listado Recepciones | F46: x | G46: x | H46: x
A47: Ajustar el servicio de facturación para validar si la factura que intentan publicar no existe registrada previamente en la addenda manual | B47: Alto | C47: David | D47: Fiscal | E47: Facturación | F47: x | G47: x | H47: x
A48: Colocar en el back la fecha del sistema en la columna fecha de recepción "Fecha Recepción" | B48: Alto | C48: David | D48: Fiscal | E48: Facturación | F48: x | G48: x | H48: x | I48: Validado por QA 29/06/2026 corregido.
A49: El reporte de recepciones cuando se consulta por tipo de proveedor no esta relacionado al catálogo de Tipo de Proveedor | B49: Alto | C49: Fernando | D49: Finanzas | E49: Listado Recepciones | F49: x | G49: x | H49: x | I49: Validado por QA 29/06/2026 corregido.
A50: Agregar la columna Guía en el grid de consulta a un lado de Orden Compra | B50: Bajo | C50: Fernando | D50: Finanzas | E50: Listado Recepciones | F50: x | G50: x | H50: x | I50: Validado por QA 29/06/2026 corregido.
A51: Cuando se hace el filtrado por proveedor retorna información de otros proveedores | B51: Alto | C51: Fernando | D51: Finanzas | E51: Listado Recepciones | F51: x | G51: x | H51: x | I51: Validado por QA 29/06/2026 no corregido.
A52: Cuando sea relacioado una recepción con una factura de manera exitosa, bloquear el botón de guardar, limpiar y la carga de documentos PDF y XML para evitar tener mas acciones que puedan afectar los datos | B52: Alto | C52: Fernando | D52: Finanzas | E52: Listado Recepciones | F52: x | G52: x | H52: x
A53: En la pantalla detalle de recepción el botón Exportar CSV colocarlo en la parte superior como botón primario. | B53: Medio | C53: Fernando | D53: Finanzas | E53: Listado Recepciones | F53: x | G53: x | H53: x | I53: Validado por QA 30/06/2026 corregido.
A54: El tipo de proveedor no se visualiza en el grid de consulta de recepciones cuando se hace un cambio en el catálogo de tipo de proveedores | B54: Medio | C54: Josue | D54: Finanzas | E54: Listado Recepciones | F54: x | G54: x | H54: x | I54: pendiente de confirmar 3 p.m.
A55: Cuando se publica una factura no cambia el estatus de la recepción a consumido cuando el valor de la factura vs recepcion es igual al 100% | B55: Alto | C55: David | D55: Finanzas | E55: Listado Recepciones | F55: x | G55: x | H55: x
A56: Cuando se publica una factura no cambia el estatus de la recepción a consumido cuando el valor de la factura vs recepcion tiene tolerancia de +-$40 | B56: Alto | C56: David | D56: Finanzas | E56: Listado Recepciones | F56: x | G56: x | H56: x
A57: Cuando se publica una factura no cambia el estatus de la recepción a consumido cuando el valor de la factura es mayor a la recepción considerando la tolerancia | B57: Alto | C57: David | D57: Finanzas | E57: Listado Recepciones | F57: x | G57: x | H57: x
A58: Ajustar la pantalla de recepciones MIGO pegando el campo de nombre archivo, botón de buscar y limpiar al lado izquierdo | B58: Bajo | C58: Oscar Bonelli | D58: Finanzas | E58: Recepciones MIGO | F58: x | G58: x | H58: x | I58: Validado por QA 30/06/2026 corregido.
A59: Los calendarios de busqueda no funcionan hasta no presionar el botón de buscar, este punto se presenta en las siguientes paginas: Aplicativo Evento Perfil Aplicativo Perfil Evento Perfil Usuario Rol Usuario Rol Permisos Usuario Atributo | B59: Bajo | C59: Roberto | D59: Seguridad | E59: Seguridad | F59: x | G59: x | H59: x
A60: Los filtros de seguridad por evento en las siguientes pantallas no esta operando | B60: Alto | C60: Ricardo | D60: Utilerias | E60: Seguridad | F60: x | G60: x | H60: x
A61: El botón de inicio en la tarjeta de utilerias no funciona, se espera que regrese al home de FBC | B61: Bajo | C61: Roberto | D61: Utilerias | E61: Utilerias | F61: x | G61: x | H61: x | I61: Validado por QA 30/06/2026 corregido.
A62: Ajustar el texto principal de la tarjeta de utilerias por Operaciones -> Auditoría y trazabilidad de eventos del módulo financiero y fiscal | B62: Bajo | C62: Roberto | D62: Utilerias | E62: Utilerias | F62: x | G62: x | H62: x | I62: Validado por QA 30/06/2026 corregido.
A63: Colocar en la parte superior de los grid de consulta el numero de registro que retorna la consulta en las siguientes pantallas Aplicativo Evento Perfil Aplicativo Perfil Evento Perfil Usuario Rol Usuario Rol Permisos Usuario Atributo | B63: Bajo | C63: Roberto | D63: Utilerias | E63: Utilerias | F63: x | G63: x | H63: x
A64: Permitir registrar una nota de crédito siempre y cuando se encuentra configurado el medio de pago de la factura en el catálogo CatFormaPagoValidoNc | B64: Alto | C64: David | D64: Fiscal | E64: Notas de crédito | F64: x | G64: x | H64: x
A65: Al publicar una OC con el listado de recepciones en el monto de la OC no presenta resultado | B65: Alto | C65: Ricardo | D65: Finanzas | E65: Recepciones MIGO | F65: x | G65: x | H65: x
A66: No permite publicar una recepción con fecha del 15/06/2026 marca error en la fecha de publicación | B66: Alto | C66: Ricardo | D66: Finanzas | E66: Recepciones MIGO | F66: x | G66: x | H66: x
A67: La fecha de publicación no se esta filtrando de manera correcta desde los campos de búsqueda | B67: Alto | C67: Ricardo | D67: Finanzas | E67: Recepciones MIGO | F67: x | G67: x | H67: x
A68: Cuando autorizada las recepciones registrarla en el módulo de “Recepciones” con el el estatus “0- Disponible” actualmente se está registrado con el valor “1 – Consumida” lo cual es incorrecto. | B68: Alto | C68: Ricardo | D68: Finanzas | E68: Recepciones MIGO | F68: x | G68: x | H68: x
A69: La fecha de registro de la recepción se esta registrando de manera incorrecta, el registro se dio de alta con la fecha del 12/06/2026 pero en el sistema se registro con la fecha del 12/06/2026 | B69: Alto | C69: Ricardo | D69: Finanzas | E69: Recepciones MIGO | F69: x | G69: x | H69: x
A70: Dejar el botón primario de “Publicar OC”, el botón de buscar y limpiar dejarlos como botones secundarios | B70: Alto | C70: Ricardo | D70: Finanzas | E70: Recepciones MIGO | F70: x | G70: x | H70: x | I70: Validado por QA 30/06/2026 corregido.
A71: Al momento de autorizar la recepción marco error | B71: Alto | C71: Ricardo | D71: Finanzas | E71: Recepciones MIGO | F71: x | G71: x | H71: x | I71: Validado por QA 30/06/2026 corregido.
A72: El calendario de búsqueda en la página de complemento de pago se pierde el mes y año en que se encuentra, además es complejo operarlo | B72: Bajo | C72: Oscar Bonelli | D72: Fiscal | E72: Complemento Pago | F72: x | G72: x | H72: x | I72: Validado por QA 30/06/2026 corregido.
A73: El calendario de búsqueda en la página de facturación se pierde el mes y año en que se encuentra, además es complejo operarlo | B73: Bajo | C73: Oscar Bonelli | D73: Fiscal | E73: Facturación | F73: x | G73: x | H73: x | I73: Validado por QA 30/06/2026 corregido.
A74: Ajustar el texto principal de la tarjeta de fiscal por: Cuéntanos, ¿Qué necesitas? -> Gestión de documentación fiscal | B74: Bajo | C74: Oscar Bonelli | D74: Fiscal | E74: Fiscal | F74: x | G74: x | H74: x | I74: Validado por QA 30/06/2026 corregido.
A75: El calendario de búsqueda en la página de notas de crédito se pierde el mes y año en que se encuentra, además es complejo operarlo | B75: Bajo | C75: Oscar Bonelli | D75: Fiscal | E75: Notas de crédito | F75: x | G75: x | H75: x | I75: Validado por QA 30/06/2026 corregido.
A76: En la pantalla de notas de crédito dejar un solo botón primario, el botón de Exportar CSV cambiarlo a blanco | B76: Bajo | C76: Oscar Bonelli | D76: Fiscal | E76: Notas de crédito | F76: x | G76: x | H76: x | I76: Validado por QA 30/06/2026 corregido.
A77: El botón de buscar en el estado de cuenta se debe presentar como botón primario | B77: Bajo | C77: Oscar Bonelli | D77: Finanzas | E77: Estado de cuenta | F77: x | G77: x | H77: x | I77: Validado por QA 30/06/2026 corregido.
A78: Ajustar el texto principal de la tarjeta de finanzas por: Operaciones -> Gestión de recepciones, pagos y descuentos | B78: Bajo | C78: Oscar Bonelli | D78: Finanzas | E78: Finanzas | F78: x | G78: x | H78: x | I78: Validado por QA 06/07/2026 corregido.
A79: Ajustar pantalla del catálogo de proveedores para validar el número de proveedor permitiendo solo registrar valores númericos | B79: Medio | C79: Ricardo | D79: Finanzas | E79: Catálogo de proveedores | F79: x | G79: x | H79: x
A80: El botón de buscar dejarlo en blanco o en botón secundario | B80: Bajo | C80: Roberto | D80: Utilerias | E80: Bitacora de actividades | F80: x | G80: x | H80: x
A81: El botón de buscar dejarlo en blanco o en botón secundario | B81: Bajo | C81: Oscar Bonelli | D81: Finanzas | E81: Recepciones MIGO | F81: x | G81: x | H81: x | I81: Validado por QA 06/07/2026 corregido.
A82: Dejar como botón primario el reporte "Exportar CSV" | B82: Bajo | C82: Oscar Bonelli | D82: Fiscal | E82: Facturación | F82: x | G82: x | H82: x
A83: Dejar como botón primario el reporte "Exportar CSV" | B83: Bajo | C83: Oscar Bonelli | D83: Fiscal | E83: Complemento Pago | F83: x | G83: x | H83: x
A84: En la consulta de la factura en la pantalla de recepción no se visualiza el documento fiscal relacionado | B84: Alto | C84: Fernando | D84: Finanzas | E84: Listado Recepciones | F84: x | G84: x | H84: x
A85: Ajustar pantalla del catálogo de bloqueo de proveedores para validar el número de proveedor permitiendo solo registrar valores númericos | B85: Medio | C85: Ricardo | D85: Finanzas | E85: Bloqueo de proveedores | F85: x | G85: x | H85: x
A86: En la pantalla de facturación el botón de Exportar CSV dejarlo como botón primario | B86: Bajo | C86: Oscar Bonelli | D86: Fiscal | E86: Facturación | F86: x | G86: x | H86: x
A87: Se intento aplicar seguridad por perfil y evento a las siguientes pantallas, las cuales no ocultaron los botones. Guías de embarque Descuentos Comerciales Pagos Estado Cuenta Three way match Publicación recepciones MIGO Facturación Notas de Crédito Complemento de Pago | B87: Alto | C87: Ricardo | D87: Utilerias | E87: Seguridad | F87: x | G87: x | H87: x | I87: En la pantalla de pagos no oculta los eventos
A88: Agregar el número de proveedor y nombre de proveedor en el listado de artículos publicados en Recepciones MIGO a un Lado de la etiqueta Monto OC | B88: Medio | C88: Ricardo | D88: Finanzas | E88: Recepciones MIGO | F88: x | G88: x | H88: x
A89: Agregar el número de proveedor en la pantalla del listado de recepciones a un lado de la columna Sucursal con los siguientes nombre Número Proveedor, Nombre Proveedor | B89: Medio | C89: Ricardo | D89: Finanzas | E89: Recepciones MIGO | F89: x | G89: x | H89: x
A90: Cambiar los titulos del grid en la pantalla de ordenes de compra por los siguientes nombres Nro. Orden de Compra -> Orden Compra Nro. Recepción -> Recepción Sucursal Agregar columna -> Número Proveedor Proveedor -> Nombre Proveedor Correo electrónico Nro. Guía -> Guía Origen Fecha Recepción Importe sin Impuestos -> Importe Monto OC | B90: Medio | C90: Ricardo | D90: Finanzas | E90: Recepciones MIGO | F90: x | G90: x | H90: x
A91: En la pantalla de detalle para visualizar las facturas relacionadas en el campo monto esta presentando el valor con impuestos, se debe presentar el valor de la factura a nivel de subtotal | B91: Alto | C91: Fernando | D91: Finanzas | E91: Listado Recepciones | F91: x | G91: x | H91: x
A92: Cuando se registra una factura con un monto superior a la recepción, presenta un mensaje de éxito, no muestra el msg de alerta indicando que se requieren agregar notas de crédito para iniciar a proceso de pago. | B92: Alto | C92: Fernando | D92: Finanzas | E92: Listado Recepciones | F92: x | G92: x | H92: x
A93: En la pantalla de notas de crédito agregar el elemento FormaPago al momento de publicar el XML de la NC | B93: Medio | C93: Fernando | D93: Fiscal | E93: Notas de crédito | F93: x | G93: x | H93: x
A94: Ajustar la pantalla de notas de crédito colocando el elemento uuid relacionado en el campo uuid relacionado | B94: Medio | C94: Fernando | D94: Fiscal | E94: Notas de crédito | F94: x | G94: x | H94: x
A95: Ajustar el servicio de consulta de documento agregando el elemento uuid relacionado | B95: Medio | C95: David | D95: Fiscal | E95: Notas de crédito | F95: x | G95: x | H95: x
A96: No permite subir una factura que no tiene serie pero si folio, la regla para publicar un documento es la siguiente: Si el documento no tiene serie y folio no debe permitir publicar la factura de lo contrario rechaza la factura o NC | B96: Medio | C96: David | D96: Fiscal | E96: Facturación | F96: x | G96: x | H96: x
A97: En la pantalla de notas de crédito dejar un botón primario activo, solo el botón de "Agregar Nota Crédito" el botón de Exportar CSV dejarlo en blanco o secundario. | B97: Bajo | C97: Fernando | D97: Fiscal | E97: Notas de crédito | F97: x | G97: x | H97: x
A98: El nombre del proveedor no se visualiza en el detalle de la recepción MIGO | B98: Medio | C98: Ricardo | D98: Finanzas | E98: Recepciones MIGO | F98: x | G98: x | H98: x
A99: Acomodar el orden del listado de la factura cuando se relaciona a la recepción RFC Emisor: CNO120829961 Nombre Proveedor: CREST NORTEAMERICA UUID: B5AF7C95-3110-4956-84AD-CDDF94A16861 Serie: Folio: 9100994004 Importe: $5,445.03 Fecha Timbrado: 14/11/2025 15:41 Uso CFDI: G01 Tipo Comprobante: I | B99: Bajo | C99: Fernando | D99: Finanzas | E99: Listado Recepciones | F99: x | G99: x | H99: x
A100: El botón para cancelar una nota de cŕedito se encuentra inactivo, se activa cuando el estatus es 3 (Pendiente) | B100: Alto | C100: Fernando | D100: Fiscal | E100: Notas de crédito | F100: x | G100: D | H100: x | I100: En revisión de los estatus de la NC
A101: Cambiar el estatus de la factura al estatus 3 En proceso de envio cuando el valor de la recepción sea igual o este dentro del valor de la tolerancia comparando la (factura - NCs) | B101: Alto | C101: David | D101: Fiscal | E101: Notas de crédito | F101: x | G101: x | H101: x
A102: Cambiar el titulo del detalle de la recepción por el siguiente nombre Facturas relacionadas - Documento fiscal relacionado | B102: Bajo | C102: Fernando | D102: Finanzas | E102: Listado Recepciones | F102: x | G102: x | H102: x
...
